Workbook

Sheet Cover
A1: Greggs plc — three-statement operating model and valuation
B3: All figures £m unless stated. Reported figures are post-IFRS 16.
B4: Scenario switch: Assumptions!C3 (Bear / Base / Bull). Changing it re-drives every forecast, schedule and valuation in this workbook.
B5: There are no circular references: interest on borrowings is charged on the opening balance, so the workbook recalculates in a single pass. Iterative calculation is enabled anyway (100 iterations, 0.0001 delta) so that a later edit introducing a circularity converges rather than erroring.
B6: FINANCING ASSUMPTION: the revolving credit facility is assumed to be upsized. Forecast borrowings peak in FY2028 in every scenario, at roughly twice the £100m facility drawn against at FY2025. Lease-inclusive net debt peaks at 1.5x EBITDA in the Base case and 1.8x in Bear, so the upsize is an assumption about facility availability, not about solvency. That is the lease-consistent measure: against a post-IFRS 16 EBITDA, gross borrowings alone would read 0.5x, which flatters the position by excluding the lease obligations the denominator has already been credited for. Both figures are on the Checks sheet.
B7: LEASE TREATMENT: post-IFRS 16 throughout, and applied identically to the DCF, the trading comps and the LBO so the three can be read against each other. EBITDA excludes rent; right-of-use depreciation sits inside D&A; new right-of-use additions are an investing outflow in unlevered free cash flow; and lease liabilities are deducted as debt in the equity bridge and carried in the debt weight of the WACC.
B8: PROVENANCE IS NOT SYMMETRIC. Greggs' own historical figures were read line by line from the annual reports and reconciled to the filings, each with a page reference (Historicals, column L). The peer figures were not: they came from results announcements, carry no page references, and three of the five peer EBITDAs are build-ups from printed components rather than printed subtotals. The load-bearing statistic — the peer median EV/EBIT — rests only on printed EBIT figures. See Comps for the detail; the two sets are in one table but are not of one standard.
B9: IMPAIRMENT CONVENTION: the historical depreciation lines include the year's net impairment, so D&A here exceeds the cash flow statement's depreciation by £3.9-6.9m a year and impairment is added back as the non-cash charge it is. One consequence is disclosed on Comps: Greggs' EBIT is struck after impairment while every peer's underlying EBIT is struck before it, so the headline EV/EBIT comparison is not like for like. Comps carries the restated, like-for-like version beside it.
B10: NOT EVERYTHING HERE IS SOURCED. The risk-free rate, equity risk premium, beta and RCF credit spread are reasoned judgement estimates; so are the £50m minimum cash floor and the LBO's 4.0x entry leverage and 20% IRR hurdle, which are conventions rather than facts. Market data — every share price, share count and the 52-week range — is a one-day observation from a price provider, not a filing. The forecast drivers are the author's assumptions and are not company guidance. Everything else is transcribed from a filing (see Historicals, column L) or derived from those transcriptions.

Sheet Checks
A1: Checks — integrity tests. Every result below must read TRUE.
B3: Balance sheet balances in every forecast year | D3: =AND(ABS('BS'!F19)<1e-06,ABS('BS'!G19)<1e-06,ABS('BS'!H19)<1e-06,ABS('BS'!I19)<1e-06,ABS('BS'!J19)<1e-06)
B4: Closing cash agrees across all three constructions of it, every year | D4: =AND(AND(ABS('CF'!F20-'BS'!F8)<1e-06,ABS('CF'!F20-'Schedules'!F48)<1e-06),AND(ABS('CF'!G20-'BS'!G8)<1e-06,ABS('CF'!G20-'Schedules'!G48)<1e-06),AND(ABS('CF'!H20-'BS'!H8)<1e-06,ABS('CF'!H20-'Schedules'!H48)<1e-06),AND(ABS('CF'!I20-'BS'!I8)<1e-06,ABS('CF'!I20-'Schedules'!I48)<1e-06),AND(ABS('CF'!J20-'BS'!J8)<1e-06,ABS('CF'!J20-'Schedules'!J48)<1e-06))
B5: Closing borrowings never negative (no accidental cash-as-debt) | D5: =AND('Schedules'!F47>=0,'Schedules'!G47>=0,'Schedules'!H47>=0,'Schedules'!I47>=0,'Schedules'!J47>=0)
B6: Cash never falls below the £50m minimum the revolver defends | D6: =AND('CF'!F20>=50.0-1e-06,'CF'!G20>=50.0-1e-06,'CF'!H20>=50.0-1e-06,'CF'!I20>=50.0-1e-06,'CF'!J20>=50.0-1e-06)
B7: Perpetuity growth is below WACC (the Gordon formula is defined) | D7: ='DCF'!$C$21<'DCF'!$C$5
B8: Terminal value is below 97% of enterprise value | D8: ='DCF'!$C$60<0.97
B9: No forecast revenue growth outside +/-50%, including the step off the last reported year | D9: =AND(ABS('IS'!F3/'Historicals'!E3-1)<0.5,ABS('IS'!G3/'IS'!F3-1)<0.5,ABS('IS'!H3/'IS'!G3-1)<0.5,ABS('IS'!I3/'IS'!H3-1)<0.5,ABS('IS'!J3/'IS'!I3-1)<0.5)
B10: Peak borrowings are an assumed facility upsize, not a solvency problem: lease-inclusive net debt / EBITDA below 2.0x every year | D10: =AND(('Schedules'!F47-'Schedules'!F48+'Schedules'!F31)/'IS'!F7<2.0,('Schedules'!G47-'Schedules'!G48+'Schedules'!G31)/'IS'!G7<2.0,('Schedules'!H47-'Schedules'!H48+'Schedules'!H31)/'IS'!H7<2.0,('Schedules'!I47-'Schedules'!I48+'Schedules'!I31)/'IS'!I7<2.0,('Schedules'!J47-'Schedules'!J48+'Schedules'!J31)/'IS'!J7<2.0)
A12: The figures behind the financing disclosure
B13: Peak forecast borrowings (£m) — against the £100m facility Greggs drew on at FY2025 (£25.0m drawn of £100m available) | C13: =MAX('Schedules'!F47,'Schedules'!G47,'Schedules'!H47,'Schedules'!I47,'Schedules'!J47)
B14: Peak lease-inclusive net debt / EBITDA (x) — the basis the check uses | C14: =MAX(('Schedules'!F47-'Schedules'!F48+'Schedules'!F31)/'IS'!F7,('Schedules'!G47-'Schedules'!G48+'Schedules'!G31)/'IS'!G7,('Schedules'!H47-'Schedules'!H48+'Schedules'!H31)/'IS'!H7,('Schedules'!I47-'Schedules'!I48+'Schedules'!I31)/'IS'!I7,('Schedules'!J47-'Schedules'!J48+'Schedules'!J31)/'IS'!J7)
B15: Memo: peak gross borrowings / EBITDA (x) — the flattering basis, shown so the difference is visible rather than hidden | C15: =MAX('Schedules'!F47/'IS'!F7,'Schedules'!G47/'IS'!G7,'Schedules'!H47/'IS'!H7,'Schedules'!I47/'IS'!I7,'Schedules'!J47/'IS'!J7)
B17: Every result above is a live formula reading the rows it tests, not a recorded outcome. Move the scenario switch on Assumptions and they re-evaluate. If any reads FALSE, the workbook is not internally consistent and nothing downstream of it should be quoted.
B18: These test internal consistency, not whether the forecast is right. A model can tie out perfectly and still be built on the wrong drivers — the Cover's disclosures and the Historicals' source column are where that question is answered.

Sheet Assumptions
A1: Assumptions — drivers and the scenario switch
F2: FY2026 | G2: FY2027 | H2: FY2028 | I2: FY2029 | J2: FY2030
B3: SCENARIO (Bear / Base / Bull) | C3: Base
A5: Scenario paths (inputs)
B6: Revenue growth — Bear | F6: 0.03 | G6: 0.025 | H6: 0.02 | I6: 0.015 | J6: 0.015
B7: Revenue growth — Base | F7: 0.06 | G7: 0.055 | H7: 0.05 | I7: 0.045 | J7: 0.045
B8: Revenue growth — Bull | F8: 0.085 | G8: 0.08 | H8: 0.075 | I8: 0.07 | J8: 0.07
B9: Gross margin — Bear | F9: 0.5996 | G9: 0.6015 | H9: 0.603 | I9: 0.604 | J9: 0.605
B10: Gross margin — Base | F10: 0.6146 | G10: 0.6165 | H10: 0.618 | I10: 0.619 | J10: 0.62
B11: Gross margin — Bull | F11: 0.6296 | G11: 0.6315 | H11: 0.633 | I11: 0.634 | J11: 0.635
B12: Operating costs (% of revenue) — Bear | F12: 0.4613 | G12: 0.458 | H12: 0.456 | I12: 0.4545 | J12: 0.453
B13: Operating costs (% of revenue) — Base | F13: 0.4513 | G13: 0.448 | H13: 0.446 | I13: 0.4445 | J13: 0.443
B14: Operating costs (% of revenue) — Bull | F14: 0.4413 | G14: 0.438 | H14: 0.436 | I14: 0.4345 | J14: 0.433
B15: Total capex (% of revenue) — Bear | F15: 0.1227 | G15: 0.111 | H15: 0.096 | I15: 0.08 | J15: 0.0682
B16: Total capex (% of revenue) — Base | F16: 0.1327 | G16: 0.121 | H16: 0.106 | I16: 0.09 | J16: 0.0777
B17: Total capex (% of revenue) — Bull | F17: 0.1407 | G17: 0.129 | H17: 0.114 | I17: 0.098 | J17: 0.0852
... B20: ROU additions (% of revenue) — Bull | F20: 0.039 | G20: 0.0404 | H20: 0.0418 | I20: 0.0432 | J20: 0.0446
B21: Exit EV/EBITDA multiple — Bear | C21: 5.07
B22: Exit EV/EBITDA multiple — Base | C22: 6.31
B23: Exit EV/EBITDA multiple — Bull | C23: 7.24
A25: Live drivers (selected by the scenario switch in C3)
B26: Revenue growth | F26: =CHOOSE(MATCH('Assumptions'!$C$3,{"Bear";"Base";"Bull"},0),'Assumptions'!F6,'Assumptions'!F7,'Assumptions'!F8) | G26: =CHOOSE(MATCH('Assumptions'!$C$3,{"Bear";"Base";"Bull"},0),'Assumptions'!G6,'Assumptions'!G7,'Assumptions'!G8) | H26: =CHOOSE(MATCH('Assumptions'!$C$3,{"Bear";"Base";"Bull"},0),'Assumptions'!H6,'Assumptions'!H7,'Assumptions'!H8) | I26: =CHOOSE(MATCH('Assumptions'!$C$3,{"Bear";"Base";"Bull"},0),'Assumptions'!I6,'Assumptions'!I7,'Assumptions'!I8) | J26: =CHOOSE(MATCH('Assumptions'!$C$3,{"Bear";"Base";"Bull"},0),'Assumptions'!J6,'Assumptions'!J7,'Assumptions'!J8)
B27: Gross margin | F27: =CHOOSE(MATCH('Assumptions'!$C$3,{"Bear";"Base";"Bull"},0),'Assumptions'!F9,'Assumptions'!F10,'Assumptions'!F11) | G27: =CHOOSE(MATCH('Assumptions'!$C$3,{"Bear";"Base";"Bull"},0),'Assumptions'!G9,'Assumptions'!G10,'Assumptions'!G11) | H27: =CHOOSE(MATCH('Assumptions'!$C$3,{"Bear";"Base";"Bull"},0),'Assumptions'!H9,'Assumptions'!H10,'Assumptions'!H11) | I27: =CHOOSE(MATCH('Assumptions'!$C$3,{"Bear";"Base";"Bull"},0),'Assumptions'!I9,'Assumptions'!I10,'Assumptions'!I11) | J27: =CHOOSE(MATCH('Assumptions'!$C$3,{"Bear";"Base";"Bull"},0),'Assumptions'!J9,'Assumptions'!J10,'Assumptions'!J11)
B28: Operating costs (% of revenue) | F28: =CHOOSE(MATCH('Assumptions'!$C$3,{"Bear";"Base";"Bull"},0),'Assumptions'!F12,'Assumptions'!F13,'Assumptions'!F14) | G28: =CHOOSE(MATCH('Assumptions'!$C$3,{"Bear";"Base";"Bull"},0),'Assumptions'!G12,'Assumptions'!G13,'Assumptions'!G14) | H28: =CHOOSE(MATCH('Assumptions'!$C$3,{"Bear";"Base";"Bull"},0),'Assumptions'!H12,'Assumptions'!H13,'Assumptions'!H14) | I28: =CHOOSE(MATCH('Assumptions'!$C$3,{"Bear";"Base";"Bull"},0),'Assumptions'!I12,'Assumptions'!I13,'Assumptions'!I14) | J28: =CHOOSE(MATCH('Assumptions'!$C$3,{"Bear";"Base";"Bull"},0),'Assumptions'!J12,'Assumptions'!J13,'Assumptions'!J14)
B29: Total capex (% of revenue) | F29: =CHOOSE(MATCH('Assumptions'!$C$3,{"Bear";"Base";"Bull"},0),'Assumptions'!F15,'Assumptions'!F16,'Assumptions'!F17) | G29: =CHOOSE(MATCH('Assumptions'!$C$3,{"Bear";"Base";"Bull"},0),'Assumptions'!G15,'Assumptions'!G16,'Assumptions'!G17) | H29: =CHOOSE(MATCH('Assumptions'!$C$3,{"Bear";"Base";"Bull"},0),'Assumptions'!H15,'Assumptions'!H16,'Assumptions'!H17) | I29: =CHOOSE(MATCH('Assumptions'!$C$3,{"Bear";"Base";"Bull"},0),'Assumptions'!I15,'Assumptions'!I16,'Assumptions'!I17) | J29: =CHOOSE(MATCH('Assumptions'!$C$3,{"Bear";"Base";"Bull"},0),'Assumptions'!J15,'Assumptions'!J16,'Assumptions'!J17)
B30: ROU additions (% of revenue) | F30: =CHOOSE(MATCH('Assumptions'!$C$3,{"Bear";"Base";"Bull"},0),'Assumptions'!F18,'Assumptions'!F19,'Assumptions'!F20) | G30: =CHOOSE(MATCH('Assumptions'!$C$3,{"Bear";"Base";"Bull"},0),'Assumptions'!G18,'Assumptions'!G19,'Assumptions'!G20) | H30: =CHOOSE(MATCH('Assumptions'!$C$3,{"Bear";"Base";"Bull"},0),'Assumptions'!H18,'Assumptions'!H19,'Assumptions'!H20) | I30: =CHOOSE(MATCH('Assumptions'!$C$3,{"Bear";"Base";"Bull"},0),'Assumptions'!I18,'Assumptions'!I19,'Assumptions'!I20) | J30: =CHOOSE(MATCH('Assumptions'!$C$3,{"Bear";"Base";"Bull"},0),'Assumptions'!J18,'Assumptions'!J19,'Assumptions'!J20)
B31: Exit EV/EBITDA multiple | C31: =CHOOSE(MATCH('Assumptions'!$C$3,{"Bear";"Base";"Bull"},0),'Assumptions'!C21,'Assumptions'!C22,'Assumptions'!C23)
A33: Operating and financing drivers (same in every scenario)
B34: Inventory days (on cost of sales) | C34: 24.5
B35: Receivable days (on revenue) | C35: 11.8
B36: Payable days (on cost of sales) | C36: 120
B37: PP&E depreciation rate (of opening PP&E) | C37: 0.1423
B38: ROU depreciation rate (of opening ROU) | C38: 0.1761
B39: Corporation tax rate | C39: 0.25
B40: Dividend payout ratio (of net income) | C40: 0.5
B41: Minimum cash balance (£m) | C41: 50
B42: Days in year (working capital basis) | C42: 365
B43: RCF interest rate (risk-free + ~150bp, estimate) | C43: 0.055
B44: Revolver interest rate (charged in the debt schedule) | C44: ='Assumptions'!$C$43
B45: Risk-free rate (UK 10-year gilt, estimate) | C45: 0.04
B46: Equity risk premium (UK, estimate) | C46: 0.055
B47: Levered equity beta (estimate) | C47: 0.9
B48: Debt weight in WACC (incl. leases) | C48: 0.2075
B49: Perpetuity growth rate | C49: 0.02
A51: Rates derived from the filings (formulas off Historicals)
B52: FY2025 interest on lease liabilities (FY2025 AR p.128) | C52: 16.7
B53: IFRS 16 lease discount rate (= FY2025 lease interest / FY2024 liability) | C53: ='Assumptions'!$C$52/'Historicals'!D30
B54: Undiscounted lease cash flows, total (FY2025 AR p.154) | C54: 582.3
B55: Undiscounted lease cash flows, < 1 year (FY2025 AR p.154) | C55: 79.1
B56: Implied average lease term, years (= total / < 1 year) | C56: ='Assumptions'!$C$54/'Assumptions'!$C$55
B57: Principal repaid on in-year lease additions (empirical fit) | C57: 0.0924
B58: Intangible share of total capex (FY2024-25 implied additions / capex) | C58: =(('Historicals'!D22-'Historicals'!C22+'Historicals'!D8)+('Historicals'!E22-'Historicals'!D22+'Historicals'!E8))/('Historicals'!D38+'Historicals'!E38)
B59: PP&E share of total capex (= 1 - intangible share) | C59: =1-'Assumptions'!$C$58
B60: Amortisation rate (= FY2025 amortisation / FY2024 intangibles) | C60: ='Historicals'!E8/'Historicals'!D22
B61: Cost of debt for the WACC (RCF/lease blend, gross-weighted) | C61: =('Historicals'!E31*'Assumptions'!$C$43+'Historicals'!E30*'Assumptions'!$C$53)/('Historicals'!E31+'Historicals'!E30)
A63: LBO sponsor assumptions (conventions, not sourced figures)
B64: Sponsor entry leverage (x EBITDA, total net debt INCLUDING leases) | C64: 4
B65: Sponsor IRR hurdle (conventional underwriting hurdle) | C65: 0.2

Sheet Historicals
A1: Historicals — Greggs plc, £m as reported (post-IFRS 16)
C2: FY2023 | D2: FY2024 | E2: FY2025
B3: Revenue | C3: 1809.6 | D3: 2014.4 | E3: 2151.2 | L3: FY2023 AR p.119 / FY2024 AR p.128 / FY2025 AR p.128
B4: Cost of sales | C4: 710.5 | D4: 770.8 | E4: 829.1 | L4: FY2023 AR p.119 / FY2024 AR p.128 / FY2025 AR p.128
B5: Operating costs (excl. D&A and impairment) | C5: 777.9 | D5: 889.2 | E5: 970.9 | L5: FY2023 AR p.119, p.124 (D&A and impairment) / FY2024 AR p.128, p.147 (D&A and impairment) / FY2025 AR p.128, p.148 (D&A and impairment)
B6: Depreciation of PP&E (incl. net impairment) | C6: 68 | D6: 79.5 | E6: 94.6 | L6: FY2023 AR p.124 / FY2024 AR p.147 (Note 3) / FY2025 AR p.148 (Note 3)
B7: Depreciation of ROU assets (incl. net impairment) | C7: 57 | D7: 61.3 | E7: 68.2 | L7: FY2023 AR p.124 / FY2024 AR p.147 (Note 3) / FY2025 AR p.148 (Note 3)
B8: Amortisation of intangibles | C8: 3.9 | D8: 4.2 | E8: 4.7 | L8: FY2023 AR p.124 / FY2024 AR p.147 (Note 3) / FY2025 AR p.148 (Note 3)
B9: Finance costs (incl. lease interest) | C9: 10.1 | D9: 13.6 | E9: 18.1 | L9: FY2024 AR p.128 (2023 comparative) / FY2024 AR p.128 / FY2025 AR p.128
B10: Finance income | C10: 6.1 | D10: 8.1 | E10: 1.8 | L10: FY2024 AR p.128 (2023 comparative) / FY2024 AR p.128 / FY2025 AR p.128
B11: Tax expense | C11: 45.8 | D11: 50.5 | E11: 45.2 | L11: FY2023 AR p.119 / FY2024 AR p.128 / FY2025 AR p.128
B12: Gross profit | C12: ='Historicals'!C3-'Historicals'!C4 | D12: ='Historicals'!D3-'Historicals'!D4 | E12: ='Historicals'!E3-'Historicals'!E4
B13: EBITDA | C13: ='Historicals'!C12-'Historicals'!C5 | D13: ='Historicals'!D12-'Historicals'!D5 | E13: ='Historicals'!E12-'Historicals'!E5
B14: Total D&A (incl. impairment) | C14: ='Historicals'!C6+'Historicals'!C7+'Historicals'!C8 | D14: ='Historicals'!D6+'Historicals'!D7+'Historicals'!D8 | E14: ='Historicals'!E6+'Historicals'!E7+'Historicals'!E8
B15: EBIT (operating profit) | C15: ='Historicals'!C13-'Historicals'!C14 | D15: ='Historicals'!D13-'Historicals'!D14 | E15: ='Historicals'!E13-'Historicals'!E14
B16: Profit before tax | C16: ='Historicals'!C15+'Historicals'!C10-'Historicals'!C9 | D16: ='Historicals'!D15+'Historicals'!D10-'Historicals'!D9 | E16: ='Historicals'!E15+'Historicals'!E10-'Historicals'!E9
B17: Net income | C17: ='Historicals'!C16-'Historicals'!C11 | D17: ='Historicals'!D16-'Historicals'!D11 | E17: ='Historicals'!E16-'Historicals'!E11
A19: Balance sheet
B20: Property, plant and equipment | C20: 510.3 | D20: 664.7 | E20: 832.1 | L20: FY2023 AR p.120 / FY2024 AR p.129 / FY2025 AR p.129
B21: Right-of-use assets | C21: 296.6 | D21: 387.2 | E21: 413 | L21: FY2023 AR p.120 / FY2024 AR p.129 / FY2025 AR p.129
B22: Intangible assets | C22: 18.3 | D22: 24.9 | E22: 43 | L22: FY2023 AR p.120 / FY2024 AR p.129 / FY2025 AR p.129
B23: Inventories | C23: 48.8 | D23: 55.2 | E23: 55.7 | L23: FY2023 AR p.120 / FY2024 AR p.129 / FY2025 AR p.129
B24: Trade and other receivables | C24: 53.8 | D24: 62.4 | E24: 69.4 | L24: FY2023 AR p.120 / FY2024 AR p.129 / FY2025 AR p.129
B25: Cash and cash equivalents | C25: 195.3 | D25: 125.3 | E25: 70.8 | L25: FY2023 AR p.120 / FY2024 AR p.129 / FY2025 AR p.129
B26: Other assets | C26: 6.6 | D26: 0 | E26: 0 | L26: FY2023 AR p.120 / FY2024 AR p.129 / FY2025 AR p.129
B27: Total assets | C27: ='Historicals'!C20+'Historicals'!C21+'Historicals'!C22+'Historicals'!C23+'Historicals'!C24+'Historicals'!C25+'Historicals'!C26 | D27: ='Historicals'!D20+'Historicals'!D21+'Historicals'!D22+'Historicals'!D23+'Historicals'!D24+'Historicals'!D25+'Historicals'!D26 | E27: ='Historicals'!E20+'Historicals'!E21+'Historicals'!E22+'Historicals'!E23+'Historicals'!E24+'Historicals'!E25+'Historicals'!E26
B29: Trade and other payables | C29: 211.1 | D29: 243.9 | E29: 272.8 | L29: FY2023 AR p.120 / FY2024 AR p.129 / FY2025 AR p.129
B30: Lease liabilities | C30: 319.6 | D30: 415.1 | E30: 449.8 | L30: FY2023 AR p.120 / FY2024 AR p.129 / FY2025 AR p.129
B31: Borrowings (RCF drawn) | C31: 0 | D31: 0 | E31: 25 | L31: FY2023 AR p.120 / FY2024 AR p.129 / FY2025 AR p.129
B32: Other liabilities | C32: 68.1 | D32: 90.2 | E32: 111.2 | L32: FY2023 AR p.120 / FY2024 AR p.129 / FY2025 AR p.129
B33: Total equity | C33: 530.9 | D33: 570.5 | E33: 625.2 | L33: FY2023 AR p.120 / FY2024 AR p.129 / FY2025 AR p.129
B34: Total liabilities and equity | C34: ='Historicals'!C29+'Historicals'!C30+'Historicals'!C31+'Historicals'!C32+'Historicals'!C33 | D34: ='Historicals'!D29+'Historicals'!D30+'Historicals'!D31+'Historicals'!D32+'Historicals'!D33 | E34: ='Historicals'!E29+'Historicals'!E30+'Historicals'!E31+'Historicals'!E32+'Historicals'!E33
B35: Net working capital | C35: ='Historicals'!C23+'Historicals'!C24-'Historicals'!C29 | D35: ='Historicals'!D23+'Historicals'!D24-'Historicals'!D29 | E35: ='Historicals'!E23+'Historicals'!E24-'Historicals'!E29
A37: Cash flow
B38: Capital expenditure (total cash, PP&E + intangibles) | C38: 198.1 | D38: 240.9 | E38: 285.4 | L38: FY2023 AR p.123 / FY2024 AR p.132 / FY2025 AR p.132
B39: Repayment of lease principal | C39: 53.7 | D39: 56.7 | E39: 63.3 | L39: FY2023 AR p.123 / FY2024 AR p.132 / FY2025 AR p.132
B40: New right-of-use asset additions | C40: 70.3 | D40: 143.8 | E40: 74.8 | L40: FY2023 AR p.144 (Note 11) / FY2024 AR p.153 (Note 11) / FY2025 AR p.154 (Note 11)
B41: Dividends paid | C41: 60.8 | D41: 106.8 | E41: 70.3 | L41: FY2023 AR p.123 / FY2024 AR p.132 / FY2025 AR p.132
A43: Share count
B44: Weighted average shares in issue, diluted (m) | E44: 102.48289 | L44: FY2025 AR p.152 (Note 9)

Sheet IS
A1: Income statement — forecast, £m
F2: ='Assumptions'!F$2 | G2: ='Assumptions'!G$2 | H2: ='Assumptions'!H$2 | I2: ='Assumptions'!I$2 | J2: ='Assumptions'!J$2
B3: Revenue | F3: ='Historicals'!E3*(1+'Assumptions'!F26) | G3: ='IS'!F3*(1+'Assumptions'!G26) | H3: ='IS'!G3*(1+'Assumptions'!H26) | I3: ='IS'!H3*(1+'Assumptions'!I26) | J3: ='IS'!I3*(1+'Assumptions'!J26)
B4: Gross profit | F4: ='IS'!F3*'Assumptions'!F27 | G4: ='IS'!G3*'Assumptions'!G27 | H4: ='IS'!H3*'Assumptions'!H27 | I4: ='IS'!I3*'Assumptions'!I27 | J4: ='IS'!J3*'Assumptions'!J27
B5: Cost of sales (memo: revenue less gross profit) | F5: ='IS'!F3-'IS'!F4 | G5: ='IS'!G3-'IS'!G4 | H5: ='IS'!H3-'IS'!H4 | I5: ='IS'!I3-'IS'!I4 | J5: ='IS'!J3-'IS'!J4
B6: Operating costs (excl. D&A) | F6: ='IS'!F3*'Assumptions'!F28 | G6: ='IS'!G3*'Assumptions'!G28 | H6: ='IS'!H3*'Assumptions'!H28 | I6: ='IS'!I3*'Assumptions'!I28 | J6: ='IS'!J3*'Assumptions'!J28
B7: EBITDA | F7: ='IS'!F4-'IS'!F6 | G7: ='IS'!G4-'IS'!G6 | H7: ='IS'!H4-'IS'!H6 | I7: ='IS'!I4-'IS'!I6 | J7: ='IS'!J4-'IS'!J6
B8: Depreciation of PP&E | F8: ='Schedules'!F13 | G8: ='Schedules'!G13 | H8: ='Schedules'!H13 | I8: ='Schedules'!I13 | J8: ='Schedules'!J13
B9: Depreciation of ROU assets | F9: ='Schedules'!F26 | G9: ='Schedules'!G26 | H9: ='Schedules'!H26 | I9: ='Schedules'!I26 | J9: ='Schedules'!J26
B10: Amortisation | F10: ='Schedules'!F19 | G10: ='Schedules'!G19 | H10: ='Schedules'!H19 | I10: ='Schedules'!I19 | J10: ='Schedules'!J19
B11: Total depreciation and amortisation | F11: ='IS'!F8+'IS'!F9+'IS'!F10 | G11: ='IS'!G8+'IS'!G9+'IS'!G10 | H11: ='IS'!H8+'IS'!H9+'IS'!H10 | I11: ='IS'!I8+'IS'!I9+'IS'!I10 | J11: ='IS'!J8+'IS'!J9+'IS'!J10
B12: EBIT | F12: ='IS'!F7-'IS'!F11 | G12: ='IS'!G7-'IS'!G11 | H12: ='IS'!H7-'IS'!H11 | I12: ='IS'!I7-'IS'!I11 | J12: ='IS'!J7-'IS'!J11
B13: Lease interest | F13: ='Schedules'!F29 | G13: ='Schedules'!G29 | H13: ='Schedules'!H29 | I13: ='Schedules'!I29 | J13: ='Schedules'!J29
B14: Interest on borrowings | F14: ='Schedules'!F43 | G14: ='Schedules'!G43 | H14: ='Schedules'!H43 | I14: ='Schedules'!I43 | J14: ='Schedules'!J43
B15: Profit before tax | F15: ='IS'!F12-'IS'!F13-'IS'!F14 | G15: ='IS'!G12-'IS'!G13-'IS'!G14 | H15: ='IS'!H12-'IS'!H13-'IS'!H14 | I15: ='IS'!I12-'IS'!I13-'IS'!I14 | J15: ='IS'!J12-'IS'!J13-'IS'!J14
B16: Tax charge (nil in a loss year) | F16: =MAX('IS'!F15,0)*'Assumptions'!$C$39 | G16: =MAX('IS'!G15,0)*'Assumptions'!$C$39 | H16: =MAX('IS'!H15,0)*'Assumptions'!$C$39 | I16: =MAX('IS'!I15,0)*'Assumptions'!$C$39 | J16: =MAX('IS'!J15,0)*'Assumptions'!$C$39
B17: Net income | F17: ='IS'!F15-'IS'!F16 | G17: ='IS'!G15-'IS'!G16 | H17: ='IS'!H15-'IS'!H16 | I17: ='IS'!I15-'IS'!I16 | J17: ='IS'!J15-'IS'!J16

Sheet BS
A1: Balance sheet — forecast, £m
F2: ='Assumptions'!F$2 | G2: ='Assumptions'!G$2 | H2: ='Assumptions'!H$2 | I2: ='Assumptions'!I$2 | J2: ='Assumptions'!J$2
B3: Property, plant and equipment | F3: ='Schedules'!F14 | G3: ='Schedules'!G14 | H3: ='Schedules'!H14 | I3: ='Schedules'!I14 | J3: ='Schedules'!J14
B4: Right-of-use assets | F4: ='Schedules'!F27 | G4: ='Schedules'!G27 | H4: ='Schedules'!H27 | I4: ='Schedules'!I27 | J4: ='Schedules'!J27
B5: Intangible assets | F5: ='Schedules'!F20 | G5: ='Schedules'!G20 | H5: ='Schedules'!H20 | I5: ='Schedules'!I20 | J5: ='Schedules'!J20
B6: Inventories | F6: ='Schedules'!F3 | G6: ='Schedules'!G3 | H6: ='Schedules'!H3 | I6: ='Schedules'!I3 | J6: ='Schedules'!J3
B7: Trade and other receivables | F7: ='Schedules'!F4 | G7: ='Schedules'!G4 | H7: ='Schedules'!H4 | I7: ='Schedules'!I4 | J7: ='Schedules'!J4
B8: Cash and cash equivalents | F8: ='CF'!F20 | G8: ='CF'!G20 | H8: ='CF'!H20 | I8: ='CF'!I20 | J8: ='CF'!J20
B9: Other assets (held flat) | F9: ='Historicals'!E26 | G9: ='Historicals'!E26 | H9: ='Historicals'!E26 | I9: ='Historicals'!E26 | J9: ='Historicals'!E26
B10: Total assets | F10: ='BS'!F3+'BS'!F4+'BS'!F5+'BS'!F6+'BS'!F7+'BS'!F8+'BS'!F9 | G10: ='BS'!G3+'BS'!G4+'BS'!G5+'BS'!G6+'BS'!G7+'BS'!G8+'BS'!G9 | H10: ='BS'!H3+'BS'!H4+'BS'!H5+'BS'!H6+'BS'!H7+'BS'!H8+'BS'!H9 | I10: ='BS'!I3+'BS'!I4+'BS'!I5+'BS'!I6+'BS'!I7+'BS'!I8+'BS'!I9 | J10: ='BS'!J3+'BS'!J4+'BS'!J5+'BS'!J6+'BS'!J7+'BS'!J8+'BS'!J9
A12: Liabilities and equity
B13: Trade and other payables | F13: ='Schedules'!F5 | G13: ='Schedules'!G5 | H13: ='Schedules'!H5 | I13: ='Schedules'!I5 | J13: ='Schedules'!J5
B14: Lease liabilities | F14: ='Schedules'!F31 | G14: ='Schedules'!G31 | H14: ='Schedules'!H31 | I14: ='Schedules'!I31 | J14: ='Schedules'!J31
B15: Borrowings | F15: ='Schedules'!F47 | G15: ='Schedules'!G47 | H15: ='Schedules'!H47 | I15: ='Schedules'!I47 | J15: ='Schedules'!J47
B16: Other liabilities (held flat) | F16: ='Historicals'!E32 | G16: ='Historicals'!E32 | H16: ='Historicals'!E32 | I16: ='Historicals'!E32 | J16: ='Historicals'!E32
B17: Total equity | F17: ='Schedules'!F36 | G17: ='Schedules'!G36 | H17: ='Schedules'!H36 | I17: ='Schedules'!I36 | J17: ='Schedules'!J36
B18: Total liabilities and equity | F18: ='BS'!F13+'BS'!F14+'BS'!F15+'BS'!F16+'BS'!F17 | G18: ='BS'!G13+'BS'!G14+'BS'!G15+'BS'!G16+'BS'!G17 | H18: ='BS'!H13+'BS'!H14+'BS'!H15+'BS'!H16+'BS'!H17 | I18: ='BS'!I13+'BS'!I14+'BS'!I15+'BS'!I16+'BS'!I17 | J18: ='BS'!J13+'BS'!J14+'BS'!J15+'BS'!J16+'BS'!J17
B19: Balance check (total assets less total claims — must be nil) | F19: ='BS'!F10-'BS'!F18 | G19: ='BS'!G10-'BS'!G18 | H19: ='BS'!H10-'BS'!H18 | I19: ='BS'!I10-'BS'!I18 | J19: ='BS'!J10-'BS'!J18

Sheet CF
A1: Cash flow statement — forecast, £m
F2: ='Assumptions'!F$2 | G2: ='Assumptions'!G$2 | H2: ='Assumptions'!H$2 | I2: ='Assumptions'!I$2 | J2: ='Assumptions'!J$2
B3: EBITDA | F3: ='IS'!F7 | G3: ='IS'!G7 | H3: ='IS'!H7 | I3: ='IS'!I7 | J3: ='IS'!J7
B4: Increase in working capital (outflow when positive) | F4: ='Schedules'!F8 | G4: ='Schedules'!G8 | H4: ='Schedules'!H8 | I4: ='Schedules'!I8 | J4: ='Schedules'!J8
B5: Tax paid | F5: ='IS'!F16 | G5: ='IS'!G16 | H5: ='IS'!H16 | I5: ='IS'!I16 | J5: ='IS'!J16
B6: Cash from operations | F6: ='CF'!F3-'CF'!F4-'CF'!F5 | G6: ='CF'!G3-'CF'!G4-'CF'!G5 | H6: ='CF'!H3-'CF'!H4-'CF'!H5 | I6: ='CF'!I3-'CF'!I4-'CF'!I5 | J6: ='CF'!J3-'CF'!J4-'CF'!J5
A8: Investing and financing
B9: Capital expenditure (total) | F9: ='Schedules'!F21 | G9: ='Schedules'!G21 | H9: ='Schedules'!H21 | I9: ='Schedules'!I21 | J9: ='Schedules'!J21
B10: of which PP&E (memo) | F10: ='Schedules'!F12 | G10: ='Schedules'!G12 | H10: ='Schedules'!H12 | I10: ='Schedules'!I12 | J10: ='Schedules'!J12
B11: of which intangible (memo) | F11: ='Schedules'!F18 | G11: ='Schedules'!G18 | H11: ='Schedules'!H18 | I11: ='Schedules'!I18 | J11: ='Schedules'!J18
B12: Lease interest paid | F12: ='Schedules'!F29 | G12: ='Schedules'!G29 | H12: ='Schedules'!H29 | I12: ='Schedules'!I29 | J12: ='Schedules'!J29
B13: Lease principal repaid | F13: ='Schedules'!F30 | G13: ='Schedules'!G30 | H13: ='Schedules'!H30 | I13: ='Schedules'!I30 | J13: ='Schedules'!J30
B14: Interest paid on borrowings | F14: ='Schedules'!F43 | G14: ='Schedules'!G43 | H14: ='Schedules'!H43 | I14: ='Schedules'!I43 | J14: ='Schedules'!J43
B15: Repayment of borrowings | F15: ='Schedules'!F45 | G15: ='Schedules'!G45 | H15: ='Schedules'!H45 | I15: ='Schedules'!I45 | J15: ='Schedules'!J45
B16: Revolver draw (inflow) | F16: ='Schedules'!F46 | G16: ='Schedules'!G46 | H16: ='Schedules'!H46 | I16: ='Schedules'!I46 | J16: ='Schedules'!J46
B17: Dividends paid | F17: ='Schedules'!F34 | G17: ='Schedules'!G34 | H17: ='Schedules'!H34 | I17: ='Schedules'!I34 | J17: ='Schedules'!J34
B18: Net change in cash | F18: ='CF'!F6-'CF'!F9-'CF'!F12-'CF'!F13-'CF'!F14-'CF'!F15+'CF'!F16-'CF'!F17 | G18: ='CF'!G6-'CF'!G9-'CF'!G12-'CF'!G13-'CF'!G14-'CF'!G15+'CF'!G16-'CF'!G17 | H18: ='CF'!H6-'CF'!H9-'CF'!H12-'CF'!H13-'CF'!H14-'CF'!H15+'CF'!H16-'CF'!H17 | I18: ='CF'!I6-'CF'!I9-'CF'!I12-'CF'!I13-'CF'!I14-'CF'!I15+'CF'!I16-'CF'!I17 | J18: ='CF'!J6-'CF'!J9-'CF'!J12-'CF'!J13-'CF'!J14-'CF'!J15+'CF'!J16-'CF'!J17
B19: Opening cash | F19: ='Historicals'!E25 | G19: ='CF'!F20 | H19: ='CF'!G20 | I19: ='CF'!H20 | J19: ='CF'!I20
B20: Closing cash | F20: ='CF'!F19+'CF'!F18 | G20: ='CF'!G19+'CF'!G18 | H20: ='CF'!H19+'CF'!H18 | I20: ='CF'!I19+'CF'!I18 | J20: ='CF'!J19+'CF'!J18

Sheet Schedules
A1: Schedules — working capital, then fixed assets, leases, equity, debt
F2: ='Assumptions'!F$2 | G2: ='Assumptions'!G$2 | H2: ='Assumptions'!H$2 | I2: ='Assumptions'!I$2 | J2: ='Assumptions'!J$2
B3: Inventories (cost of sales x inventory days / 365) | F3: ='IS'!F5*'Assumptions'!$C$34/'Assumptions'!$C$42 | G3: ='IS'!G5*'Assumptions'!$C$34/'Assumptions'!$C$42 | H3: ='IS'!H5*'Assumptions'!$C$34/'Assumptions'!$C$42 | I3: ='IS'!I5*'Assumptions'!$C$34/'Assumptions'!$C$42 | J3: ='IS'!J5*'Assumptions'!$C$34/'Assumptions'!$C$42
B4: Trade receivables (revenue x receivable days / 365) | F4: ='IS'!F3*'Assumptions'!$C$35/'Assumptions'!$C$42 | G4: ='IS'!G3*'Assumptions'!$C$35/'Assumptions'!$C$42 | H4: ='IS'!H3*'Assumptions'!$C$35/'Assumptions'!$C$42 | I4: ='IS'!I3*'Assumptions'!$C$35/'Assumptions'!$C$42 | J4: ='IS'!J3*'Assumptions'!$C$35/'Assumptions'!$C$42
B5: Trade payables (cost of sales x payable days / 365) | F5: ='IS'!F5*'Assumptions'!$C$36/'Assumptions'!$C$42 | G5: ='IS'!G5*'Assumptions'!$C$36/'Assumptions'!$C$42 | H5: ='IS'!H5*'Assumptions'!$C$36/'Assumptions'!$C$42 | I5: ='IS'!I5*'Assumptions'!$C$36/'Assumptions'!$C$42 | J5: ='IS'!J5*'Assumptions'!$C$36/'Assumptions'!$C$42
B6: Net working capital | F6: ='Schedules'!F3+'Schedules'!F4-'Schedules'!F5 | G6: ='Schedules'!G3+'Schedules'!G4-'Schedules'!G5 | H6: ='Schedules'!H3+'Schedules'!H4-'Schedules'!H5 | I6: ='Schedules'!I3+'Schedules'!I4-'Schedules'!I5 | J6: ='Schedules'!J3+'Schedules'!J4-'Schedules'!J5
B7: Opening net working capital | F7: ='Historicals'!E35 | G7: ='Schedules'!F6 | H7: ='Schedules'!G6 | I7: ='Schedules'!H6 | J7: ='Schedules'!I6
B8: Increase in net working capital (cash outflow when positive) | F8: ='Schedules'!F6-'Schedules'!F7 | G8: ='Schedules'!G6-'Schedules'!G7 | H8: ='Schedules'!H6-'Schedules'!H7 | I8: ='Schedules'!I6-'Schedules'!I7 | J8: ='Schedules'!J6-'Schedules'!J7
A10: Fixed assets (PP&E)
B11: Opening PP&E | F11: ='Historicals'!E20 | G11: ='Schedules'!F14 | H11: ='Schedules'!G14 | I11: ='Schedules'!H14 | J11: ='Schedules'!I14
B12: PP&E capex (revenue x total capex % x PP&E share) | F12: ='IS'!F3*'Assumptions'!F29*'Assumptions'!$C$59 | G12: ='IS'!G3*'Assumptions'!G29*'Assumptions'!$C$59 | H12: ='IS'!H3*'Assumptions'!H29*'Assumptions'!$C$59 | I12: ='IS'!I3*'Assumptions'!I29*'Assumptions'!$C$59 | J12: ='IS'!J3*'Assumptions'!J29*'Assumptions'!$C$59
B13: Depreciation of PP&E (rate on opening balance) | F13: ='Schedules'!F11*'Assumptions'!$C$37 | G13: ='Schedules'!G11*'Assumptions'!$C$37 | H13: ='Schedules'!H11*'Assumptions'!$C$37 | I13: ='Schedules'!I11*'Assumptions'!$C$37 | J13: ='Schedules'!J11*'Assumptions'!$C$37
B14: Closing PP&E | F14: ='Schedules'!F11+'Schedules'!F12-'Schedules'!F13 | G14: ='Schedules'!G11+'Schedules'!G12-'Schedules'!G13 | H14: ='Schedules'!H11+'Schedules'!H12-'Schedules'!H13 | I14: ='Schedules'!I11+'Schedules'!I12-'Schedules'!I13 | J14: ='Schedules'!J11+'Schedules'!J12-'Schedules'!J13
A16: Intangible assets
B17: Opening intangibles | F17: ='Historicals'!E22 | G17: ='Schedules'!F20 | H17: ='Schedules'!G20 | I17: ='Schedules'!H20 | J17: ='Schedules'!I20
B18: Intangible additions (revenue x total capex % x intangible share) | F18: ='IS'!F3*'Assumptions'!F29*'Assumptions'!$C$58 | G18: ='IS'!G3*'Assumptions'!G29*'Assumptions'!$C$58 | H18: ='IS'!H3*'Assumptions'!H29*'Assumptions'!$C$58 | I18: ='IS'!I3*'Assumptions'!I29*'Assumptions'!$C$58 | J18: ='IS'!J3*'Assumptions'!J29*'Assumptions'!$C$58
B19: Amortisation (rate on opening balance) | F19: ='Schedules'!F17*'Assumptions'!$C$60 | G19: ='Schedules'!G17*'Assumptions'!$C$60 | H19: ='Schedules'!H17*'Assumptions'!$C$60 | I19: ='Schedules'!I17*'Assumptions'!$C$60 | J19: ='Schedules'!J17*'Assumptions'!$C$60
B20: Closing intangibles | F20: ='Schedules'!F17+'Schedules'!F18-'Schedules'!F19 | G20: ='Schedules'!G17+'Schedules'!G18-'Schedules'!G19 | H20: ='Schedules'!H17+'Schedules'!H18-'Schedules'!H19 | I20: ='Schedules'!I17+'Schedules'!I18-'Schedules'!I19 | J20: ='Schedules'!J17+'Schedules'!J18-'Schedules'!J19
B21: Total cash capex (PP&E + intangible) | F21: ='Schedules'!F12+'Schedules'!F18 | G21: ='Schedules'!G12+'Schedules'!G18 | H21: ='Schedules'!H12+'Schedules'!H18 | I21: ='Schedules'!I12+'Schedules'!I18 | J21: ='Schedules'!J12+'Schedules'!J18
A23: Leases (IFRS 16)
B24: Opening right-of-use assets | F24: ='Historicals'!E21 | G24: ='Schedules'!F27 | H24: ='Schedules'!G27 | I24: ='Schedules'!H27 | J24: ='Schedules'!I27
B25: New ROU asset additions (revenue x ROU additions %) | F25: ='IS'!F3*'Assumptions'!F30 | G25: ='IS'!G3*'Assumptions'!G30 | H25: ='IS'!H3*'Assumptions'!H30 | I25: ='IS'!I3*'Assumptions'!I30 | J25: ='IS'!J3*'Assumptions'!J30
B26: Depreciation of ROU assets (rate on opening balance) | F26: ='Schedules'!F24*'Assumptions'!$C$38 | G26: ='Schedules'!G24*'Assumptions'!$C$38 | H26: ='Schedules'!H24*'Assumptions'!$C$38 | I26: ='Schedules'!I24*'Assumptions'!$C$38 | J26: ='Schedules'!J24*'Assumptions'!$C$38
B27: Closing right-of-use assets | F27: ='Schedules'!F24+'Schedules'!F25-'Schedules'!F26 | G27: ='Schedules'!G24+'Schedules'!G25-'Schedules'!G26 | H27: ='Schedules'!H24+'Schedules'!H25-'Schedules'!H26 | I27: ='Schedules'!I24+'Schedules'!I25-'Schedules'!I26 | J27: ='Schedules'!J24+'Schedules'!J25-'Schedules'!J26
B28: Opening lease liabilities | F28: ='Historicals'!E30 | G28: ='Schedules'!F31 | H28: ='Schedules'!G31 | I28: ='Schedules'!H31 | J28: ='Schedules'!I31
B29: Lease interest (discount rate on opening liability) | F29: ='Schedules'!F28*'Assumptions'!$C$53 | G29: ='Schedules'!G28*'Assumptions'!$C$53 | H29: ='Schedules'!H28*'Assumptions'!$C$53 | I29: ='Schedules'!I28*'Assumptions'!$C$53 | J29: ='Schedules'!J28*'Assumptions'!$C$53
B30: Lease principal repaid (opening / implied term + additions x fit rate) | F30: ='Schedules'!F28/'Assumptions'!$C$56+'Schedules'!F25*'Assumptions'!$C$57 | G30: ='Schedules'!G28/'Assumptions'!$C$56+'Schedules'!G25*'Assumptions'!$C$57 | H30: ='Schedules'!H28/'Assumptions'!$C$56+'Schedules'!H25*'Assumptions'!$C$57 | I30: ='Schedules'!I28/'Assumptions'!$C$56+'Schedules'!I25*'Assumptions'!$C$57 | J30: ='Schedules'!J28/'Assumptions'!$C$56+'Schedules'!J25*'Assumptions'!$C$57
B31: Closing lease liabilities | F31: ='Schedules'!F28+'Schedules'!F25-'Schedules'!F30 | G31: ='Schedules'!G28+'Schedules'!G25-'Schedules'!G30 | H31: ='Schedules'!H28+'Schedules'!H25-'Schedules'!H30 | I31: ='Schedules'!I28+'Schedules'!I25-'Schedules'!I30 | J31: ='Schedules'!J28+'Schedules'!J25-'Schedules'!J30
A33: Equity and distributions
B34: Dividends declared (payout ratio on net income, floored at nil) | F34: =MAX('IS'!F17,0)*'Assumptions'!$C$40 | G34: =MAX('IS'!G17,0)*'Assumptions'!$C$40 | H34: =MAX('IS'!H17,0)*'Assumptions'!$C$40 | I34: =MAX('IS'!I17,0)*'Assumptions'!$C$40 | J34: =MAX('IS'!J17,0)*'Assumptions'!$C$40
B35: Opening shareholders' equity | F35: ='Historicals'!E33 | G35: ='Schedules'!F36 | H35: ='Schedules'!G36 | I35: ='Schedules'!H36 | J35: ='Schedules'!I36
B36: Closing shareholders' equity | F36: ='Schedules'!F35+'IS'!F17-'Schedules'!F34 | G36: ='Schedules'!G35+'IS'!G17-'Schedules'!G34 | H36: ='Schedules'!H35+'IS'!H17-'Schedules'!H34 | I36: ='Schedules'!I35+'IS'!I17-'Schedules'!I34 | J36: ='Schedules'!J35+'IS'!J17-'Schedules'!J34
A38: Debt and cash
B39: Cash generated before financing | F39: ='IS'!F7-'Schedules'!F8-'Schedules'!F21-'Schedules'!F30-'Schedules'!F29-'IS'!F16-'Schedules'!F34 | G39: ='IS'!G7-'Schedules'!G8-'Schedules'!G21-'Schedules'!G30-'Schedules'!G29-'IS'!G16-'Schedules'!G34 | H39: ='IS'!H7-'Schedules'!H8-'Schedules'!H21-'Schedules'!H30-'Schedules'!H29-'IS'!H16-'Schedules'!H34 | I39: ='IS'!I7-'Schedules'!I8-'Schedules'!I21-'Schedules'!I30-'Schedules'!I29-'IS'!I16-'Schedules'!I34 | J39: ='IS'!J7-'Schedules'!J8-'Schedules'!J21-'Schedules'!J30-'Schedules'!J29-'IS'!J16-'Schedules'!J34
B40: Opening borrowings | F40: ='Historicals'!E31 | G40: ='Schedules'!F47 | H40: ='Schedules'!G47 | I40: ='Schedules'!H47 | J40: ='Schedules'!I47
B41: Opening cash | F41: ='Historicals'!E25 | G41: ='Schedules'!F48 | H41: ='Schedules'!G48 | I41: ='Schedules'!H48 | J41: ='Schedules'!I48
B42: Cash available before interest | F42: ='Schedules'!F41+'Schedules'!F39 | G42: ='Schedules'!G41+'Schedules'!G39 | H42: ='Schedules'!H41+'Schedules'!H39 | I42: ='Schedules'!I41+'Schedules'!I39 | J42: ='Schedules'!J41+'Schedules'!J39
B43: Interest on borrowings (rate on opening debt) | F43: ='Schedules'!F40*'Assumptions'!$C$44 | G43: ='Schedules'!G40*'Assumptions'!$C$44 | H43: ='Schedules'!H40*'Assumptions'!$C$44 | I43: ='Schedules'!I40*'Assumptions'!$C$44 | J43: ='Schedules'!J40*'Assumptions'!$C$44
B44: Cash available before debt service | F44: ='Schedules'!F42-'Schedules'!F43 | G44: ='Schedules'!G42-'Schedules'!G43 | H44: ='Schedules'!H42-'Schedules'!H43 | I44: ='Schedules'!I42-'Schedules'!I43 | J44: ='Schedules'!J42-'Schedules'!J43
B45: Repayment of borrowings | F45: =MAX(0,MIN('Schedules'!F40,'Schedules'!F44-'Assumptions'!$C$41)) | G45: =MAX(0,MIN('Schedules'!G40,'Schedules'!G44-'Assumptions'!$C$41)) | H45: =MAX(0,MIN('Schedules'!H40,'Schedules'!H44-'Assumptions'!$C$41)) | I45: =MAX(0,MIN('Schedules'!I40,'Schedules'!I44-'Assumptions'!$C$41)) | J45: =MAX(0,MIN('Schedules'!J40,'Schedules'!J44-'Assumptions'!$C$41))
B46: Revolver draw | F46: =MAX(0,'Assumptions'!$C$41-'Schedules'!F44) | G46: =MAX(0,'Assumptions'!$C$41-'Schedules'!G44) | H46: =MAX(0,'Assumptions'!$C$41-'Schedules'!H44) | I46: =MAX(0,'Assumptions'!$C$41-'Schedules'!I44) | J46: =MAX(0,'Assumptions'!$C$41-'Schedules'!J44)
B47: Closing borrowings | F47: ='Schedules'!F40-'Schedules'!F45+'Schedules'!F46 | G47: ='Schedules'!G40-'Schedules'!G45+'Schedules'!G46 | H47: ='Schedules'!H40-'Schedules'!H45+'Schedules'!H46 | I47: ='Schedules'!I40-'Schedules'!I45+'Schedules'!I46 | J47: ='Schedules'!J40-'Schedules'!J45+'Schedules'!J46
B48: Closing cash (debt schedule's own track) | F48: ='Schedules'!F44-'Schedules'!F45+'Schedules'!F46 | G48: ='Schedules'!G44-'Schedules'!G45+'Schedules'!G46 | H48: ='Schedules'!H44-'Schedules'!H45+'Schedules'!H46 | I48: ='Schedules'!I44-'Schedules'!I45+'Schedules'!I46 | J48: ='Schedules'!J44-'Schedules'!J45+'Schedules'!J46

Sheet DCF
A1: Discounted cash flow — Gordon growth on a re-based terminal year, £m
F2: ='Assumptions'!F$2 | G2: ='Assumptions'!G$2 | H2: ='Assumptions'!H$2 | I2: ='Assumptions'!I$2 | J2: ='Assumptions'!J$2
B3: Cost of equity (CAPM: risk-free rate + beta x equity risk premium) | C3: ='Assumptions'!$C$45+'Assumptions'!$C$47*'Assumptions'!$C$46
B4: After-tax cost of debt (blended rate x (1 - tax rate)) | C4: ='Assumptions'!$C$61*(1-'Assumptions'!$C$39)
B5: WACC | C5: =(1-'Assumptions'!$C$48)*'DCF'!$C$3+'Assumptions'!$C$48*'DCF'!$C$4
A7: Unlevered free cash flow — the explicit five years
B8: EBIT (from the income statement) | F8: ='IS'!F12 | G8: ='IS'!G12 | H8: ='IS'!H12 | I8: ='IS'!I12 | J8: ='IS'!J12
B9: EBIT after tax (unlevered: nothing below EBIT enters this sheet) | F9: ='DCF'!F8*(1-'Assumptions'!$C$39) | G9: ='DCF'!G8*(1-'Assumptions'!$C$39) | H9: ='DCF'!H8*(1-'Assumptions'!$C$39) | I9: ='DCF'!I8*(1-'Assumptions'!$C$39) | J9: ='DCF'!J8*(1-'Assumptions'!$C$39)
B10: Depreciation and amortisation (added back) | F10: ='IS'!F11 | G10: ='IS'!G11 | H10: ='IS'!H11 | I10: ='IS'!I11 | J10: ='IS'!J11
B11: Total cash capex (PP&E + intangible) | F11: ='Schedules'!F21 | G11: ='Schedules'!G21 | H11: ='Schedules'!H21 | I11: ='Schedules'!I21 | J11: ='Schedules'!J21
B12: New ROU asset additions (an investing outflow — leases are debt here) | F12: ='Schedules'!F25 | G12: ='Schedules'!G25 | H12: ='Schedules'!H25 | I12: ='Schedules'!I25 | J12: ='Schedules'!J25
B13: Increase in net working capital | F13: ='Schedules'!F8 | G13: ='Schedules'!G8 | H13: ='Schedules'!H8 | I13: ='Schedules'!I8 | J13: ='Schedules'!J8
B14: Unlevered free cash flow | F14: ='DCF'!F9+'DCF'!F10-'DCF'!F11-'DCF'!F12-'DCF'!F13 | G14: ='DCF'!G9+'DCF'!G10-'DCF'!G11-'DCF'!G12-'DCF'!G13 | H14: ='DCF'!H9+'DCF'!H10-'DCF'!H11-'DCF'!H12-'DCF'!H13 | I14: ='DCF'!I9+'DCF'!I10-'DCF'!I11-'DCF'!I12-'DCF'!I13 | J14: ='DCF'!J9+'DCF'!J10-'DCF'!J11-'DCF'!J12-'DCF'!J13
B15: Discount period (years, mid-year convention) | F15: =COLUMN()-COLUMN('DCF'!$F$14)+0.5 | G15: =COLUMN()-COLUMN('DCF'!$F$14)+0.5 | H15: =COLUMN()-COLUMN('DCF'!$F$14)+0.5 | I15: =COLUMN()-COLUMN('DCF'!$F$14)+0.5 | J15: =COLUMN()-COLUMN('DCF'!$F$14)+0.5
B16: Discount factor | F16: =(1+'DCF'!$C$5)^'DCF'!F15 | G16: =(1+'DCF'!$C$5)^'DCF'!G15 | H16: =(1+'DCF'!$C$5)^'DCF'!H15 | I16: =(1+'DCF'!$C$5)^'DCF'!I15 | J16: =(1+'DCF'!$C$5)^'DCF'!J15
B17: PV of unlevered free cash flow | F17: ='DCF'!F14/'DCF'!F16 | G17: ='DCF'!G14/'DCF'!G16 | H17: ='DCF'!H14/'DCF'!H16 | I17: ='DCF'!I14/'DCF'!I16 | J17: ='DCF'!J14/'DCF'!J16
A19: Terminal year — the final year rebuilt at the perpetuity growth rate
B20: This block is NOT FY2030. Every investment and depreciation intensity below is re-derived at the perpetuity growth rate g*, because FY2030's were derived to sustain the estate at that scenario's own terminal revenue growth and still carry the tail of the distribution-centre programme. The revenue LEVEL is FY2030's; the (1 + g*) step to the first perpetuity year is applied by the Gordon formula below.
B21: Perpetuity growth rate (g*) | C21: ='Assumptions'!$C$49
B22: Terminal PP&E / revenue (post-programme anchor) | C22: =('BS'!J3/'IS'!J3)/(1+'DCF'!$C$21)^(1/'Assumptions'!$C$37)
B23: Terminal ROU assets / revenue (FY2025 actual) | C23: ='Historicals'!E21/'Historicals'!E3
B24: Terminal total capex (% of revenue, sustaining, grossed up for intangibles) | C24: ='DCF'!$C$22*('DCF'!$C$21+'Assumptions'!$C$37)/(1+'DCF'!$C$21)/'Assumptions'!$C$59
B25: Terminal ROU additions (% of revenue, sustaining) | C25: ='DCF'!$C$23*('DCF'!$C$21+'Assumptions'!$C$38)/(1+'DCF'!$C$21)
B26: Terminal PP&E depreciation (% of revenue) | C26: ='Assumptions'!$C$37*'DCF'!$C$22/(1+'DCF'!$C$21)
B27: Terminal ROU depreciation (% of revenue) | C27: ='Assumptions'!$C$38*'DCF'!$C$23/(1+'DCF'!$C$21)
B28: Terminal intangible additions (% of revenue) | C28: ='DCF'!$C$24*'Assumptions'!$C$58
B29: Terminal amortisation (% of revenue) | C29: ='DCF'!$C$28*'Assumptions'!$C$60/('DCF'!$C$21+'Assumptions'!$C$60)
B30: Terminal D&A (% of revenue) | C30: ='DCF'!$C$26+'DCF'!$C$27+'DCF'!$C$29
B31: Terminal net working capital (% of revenue, negative — payables dominate) | C31: ='Schedules'!J6/'IS'!J3
B32: Terminal revenue (the FY2030 LEVEL, not FY2031's) | C32: ='IS'!J3
B33: Terminal EBITDA margin (FY2030 gross margin less FY2030 opex ratio) | C33: ='Assumptions'!J27-'Assumptions'!J28
B34: Terminal EBITDA (margin x revenue) | C34: ='DCF'!$C$33*'DCF'!$C$32
B35: Terminal depreciation and amortisation | C35: ='DCF'!$C$30*'DCF'!$C$32
B36: Terminal EBIT | C36: ='DCF'!$C$34-'DCF'!$C$35
B37: Terminal total cash capex | C37: ='DCF'!$C$24*'DCF'!$C$32
B38: Terminal ROU asset additions | C38: ='DCF'!$C$25*'DCF'!$C$32
B39: Terminal increase in net working capital (negative = cash released) | C39: ='DCF'!$C$31*'DCF'!$C$21/(1+'DCF'!$C$21)*'DCF'!$C$32
B40: Terminal unlevered free cash flow | C40: ='DCF'!$C$36*(1-'Assumptions'!$C$39)+'DCF'!$C$35-'DCF'!$C$37-'DCF'!$C$38-'DCF'!$C$39
B41: Terminal D&A / EBITDA (the capital intensity Comps prices) | C41: ='DCF'!$C$35/'DCF'!$C$34
A43: Terminal value
B44: Terminal value (Gordon growth) | C44: ='DCF'!$C$40*(1+'DCF'!$C$21)/('DCF'!$C$5-'DCF'!$C$21)
B45: Excess PP&E over the re-based base, at FY2029 | C45: ='BS'!I3-'DCF'!$C$22*'IS'!I3
B46: Decay factor x = (1 - PP&E depreciation rate) / (1 + WACC) | C46: =(1-'Assumptions'!$C$37)/(1+'DCF'!$C$5)
B47: Value at the terminal date of the excess PP&E tax shield | C47: ='Assumptions'!$C$39*'Assumptions'!$C$37*'DCF'!$C$45*'DCF'!$C$46/(1-'DCF'!$C$46)
B48: Terminal value (exit multiple) | C48: ='IS'!J7*'Assumptions'!$C$31
B49: READ THIS BEFORE USING THE ROW ABOVE: it is NOT an independent second method and it must not be taken as corroboration of the Gordon value. EV/EBITDA = EV/EBIT x (1 - D&A/EBITDA) is an identity, and the exit multiple on Assumptions IS the peer median EV/EBIT read at this terminal year's own D&A/EBITDA, so the EBITDA cancels and this row is exactly the peer median EV/EBIT x terminal EBIT — one peer statistic (the median of five is J D Wetherspoon alone) applied to the model's own EBIT. The two rows that follow are the proof. It builds no part of the enterprise value below.
B50: Memo: exit-multiple TV / terminal EBIT (equals the peer median EV/EBIT) | C50: ='DCF'!$C$48/'DCF'!$C$36
B51: Memo: peer median EV/EBIT from Comps (the row above, to 2dp rounding) | C51: ='Comps'!$J$18
B52: Gordon terminal value / terminal EBITDA (the multiple Gordon implies) | C52: ='DCF'!$C$44/'DCF'!$C$34
B53: Gordon terminal value / terminal EBIT (the like-for-like peer comparison) | C53: ='DCF'!$C$44/'DCF'!$C$36
B54: The comparison to make against the peer set is the EV/EBIT one, not the EV/EBITDA one. The model deliberately builds a more capital-intensive Greggs by FY2030, and a higher D&A share mechanically lowers the coherent EBITDA multiple without saying anything about rating: across the three scenarios the Gordon terminal value sits 14% to 26% below the peer median on EV/EBIT against 17% to 50% below on EV/EBITDA. What is left after that artefact is a real disagreement about terminal reinvestment intensity, and it is not tuned away.
A56: Enterprise value and the bridge to equity
B57: PV of the explicit forecast period | C57: ='DCF'!F17+'DCF'!G17+'DCF'!H17+'DCF'!I17+'DCF'!J17
B58: PV of the terminal value (Gordon plus the excess PP&E shield) | C58: =('DCF'!$C$44+'DCF'!$C$47)/'DCF'!J16
B59: Enterprise value | C59: ='DCF'!$C$57+'DCF'!$C$58
B60: Terminal value as a share of enterprise value | C60: ='DCF'!$C$58/'DCF'!$C$59
B61: Net debt at FY2025 (borrowings less cash, excluding leases) | C61: ='Historicals'!E31-'Historicals'!E25
B62: Lease liabilities at FY2025 (deducted as debt, as in the WACC weight) | C62: ='Historicals'!E30
B63: Equity value | C63: ='DCF'!$C$59-'DCF'!$C$61-'DCF'!$C$62
B64: Shares in issue (weighted average diluted, m) | C64: ='Historicals'!E44
B65: Implied share price (p) | C65: ='DCF'!$C$63/'DCF'!$C$64*100
B66: Implied share price against the traded price on Comps | C66: ='DCF'!$C$65/'Comps'!$C$24-1

Sheet Sensitivity
A1: Sensitivity — every cell recomputed from its own axis pair
A3: Implied share price (p) — perpetuity growth across, WACC down. The centre cell is the DCF's own answer.
B4: Perpetuity growth (across) | D4: ='DCF'!$C$21-0.005 | E4: ='DCF'!$C$21-0.0025 | F4: ='DCF'!$C$21 | G4: ='DCF'!$C$21+0.0025 | H4: ='DCF'!$C$21+0.005
B5: WACC less 100bp | C5: ='DCF'!$C$5-0.01 | D5: =('DCF'!$F$14/(1+$C5)^'DCF'!$F$15+'DCF'!$G$14/(1+$C5)^'DCF'!$G$15+'DCF'!$H$14/(1+$C5)^'DCF'!$H$15+'DCF'!$I$14/(1+$C5)^'DCF'!$I$15+'DCF'!$J$14/(1+$C5)^'DCF'!$J$15+('Sensitivity'!D26*(1+D$4)/($C5-D$4)+'Assumptions'!$C$39*'Assumptions'!$C$37*'Sensitivity'!D27*(1-'Assumptions'!$C$37)/(1+$C5)/(1-(1-'Assumptions'!$C$37)/(1+$C5)))/(1+$C5)^'DCF'!$J$15-'DCF'!$C$61-'DCF'!$C$62)/'DCF'!$C$64*100 | E5: =('DCF'!$F$14/(1+$C5)^'DCF'!$F$15+'DCF'!$G$14/(1+$C5)^'DCF'!$G$15+'DCF'!$H$14/(1+$C5)^'DCF'!$H$15+'DCF'!$I$14/(1+$C5)^'DCF'!$I$15+'DCF'!$J$14/(1+$C5)^'DCF'!$J$15+('Sensitivity'!E26*(1+E$4)/($C5-E$4)+'Assumptions'!$C$39*'Assumptions'!$C$37*'Sensitivity'!E27*(1-'Assumptions'!$C$37)/(1+$C5)/(1-(1-'Assumptions'!$C$37)/(1+$C5)))/(1+$C5)^'DCF'!$J$15-'DCF'!$C$61-'DCF'!$C$62)/'DCF'!$C$64*100 | F5: =('DCF'!$F$14/(1+$C5)^'DCF'!$F$15+'DCF'!$G$14/(1+$C5)^'DCF'!$G$15+'DCF'!$H$14/(1+$C5)^'DCF'!$H$15+'DCF'!$I$14/(1+$C5)^'DCF'!$I$15+'DCF'!$J$14/(1+$C5)^'DCF'!$J$15+('Sensitivity'!F26*(1+F$4)/($C5-F$4)+'Assumptions'!$C$39*'Assumptions'!$C$37*'Sensitivity'!F27*(1-'Assumptions'!$C$37)/(1+$C5)/(1-(1-'Assumptions'!$C$37)/(1+$C5)))/(1+$C5)^'DCF'!$J$15-'DCF'!$C$61-'DCF'!$C$62)/'DCF'!$C$64*100 | G5: =('DCF'!$F$14/(1+$C5)^'DCF'!$F$15+'DCF'!$G$14/(1+$C5)^'DCF'!$G$15+'DCF'!$H$14/(1+$C5)^'DCF'!$H$15+'DCF'!$I$14/(1+$C5)^'DCF'!$I$15+'DCF'!$J$14/(1+$C5)^'DCF'!$J$15+('Sensitivity'!G26*(1+G$4)/($C5-G$4)+'Assumptions'!$C$39*'Assumptions'!$C$37*'Sensitivity'!G27*(1-'Assumptions'!$C$37)/(1+$C5)/(1-(1-'Assumptions'!$C$37)/(1+$C5)))/(1+$C5)^'DCF'!$J$15-'DCF'!$C$61-'DCF'!$C$62)/'DCF'!$C$64*100 | H5: =('DCF'!$F$14/(1+$C5)^'DCF'!$F$15+'DCF'!$G$14/(1+$C5)^'DCF'!$G$15+'DCF'!$H$14/(1+$C5)^'DCF'!$H$15+'DCF'!$I$14/(1+$C5)^'DCF'!$I$15+'DCF'!$J$14/(1+$C5)^'DCF'!$J$15+('Sensitivity'!H26*(1+H$4)/($C5-H$4)+'Assumptions'!$C$39*'Assumptions'!$C$37*'Sensitivity'!H27*(1-'Assumptions'!$C$37)/(1+$C5)/(1-(1-'Assumptions'!$C$37)/(1+$C5)))/(1+$C5)^'DCF'!$J$15-'DCF'!$C$61-'DCF'!$C$62)/'DCF'!$C$64*100
B6: WACC less 50bp | C6: ='DCF'!$C$5-0.005 | D6: =('DCF'!$F$14/(1+$C6)^'DCF'!$F$15+'DCF'!$G$14/(1+$C6)^'DCF'!$G$15+'DCF'!$H$14/(1+$C6)^'DCF'!$H$15+'DCF'!$I$14/(1+$C6)^'DCF'!$I$15+'DCF'!$J$14/(1+$C6)^'DCF'!$J$15+('Sensitivity'!D26*(1+D$4)/($C6-D$4)+'Assumptions'!$C$39*'Assumptions'!$C$37*'Sensitivity'!D27*(1-'Assumptions'!$C$37)/(1+$C6)/(1-(1-'Assumptions'!$C$37)/(1+$C6)))/(1+$C6)^'DCF'!$J$15-'DCF'!$C$61-'DCF'!$C$62)/'DCF'!$C$64*100 | E6: =('DCF'!$F$14/(1+$C6)^'DCF'!$F$15+'DCF'!$G$14/(1+$C6)^'DCF'!$G$15+'DCF'!$H$14/(1+$C6)^'DCF'!$H$15+'DCF'!$I$14/(1+$C6)^'DCF'!$I$15+'DCF'!$J$14/(1+$C6)^'DCF'!$J$15+('Sensitivity'!E26*(1+E$4)/($C6-E$4)+'Assumptions'!$C$39*'Assumptions'!$C$37*'Sensitivity'!E27*(1-'Assumptions'!$C$37)/(1+$C6)/(1-(1-'Assumptions'!$C$37)/(1+$C6)))/(1+$C6)^'DCF'!$J$15-'DCF'!$C$61-'DCF'!$C$62)/'DCF'!$C$64*100 | F6: =('DCF'!$F$14/(1+$C6)^'DCF'!$F$15+'DCF'!$G$14/(1+$C6)^'DCF'!$G$15+'DCF'!$H$14/(1+$C6)^'DCF'!$H$15+'DCF'!$I$14/(1+$C6)^'DCF'!$I$15+'DCF'!$J$14/(1+$C6)^'DCF'!$J$15+('Sensitivity'!F26*(1+F$4)/($C6-F$4)+'Assumptions'!$C$39*'Assumptions'!$C$37*'Sensitivity'!F27*(1-'Assumptions'!$C$37)/(1+$C6)/(1-(1-'Assumptions'!$C$37)/(1+$C6)))/(1+$C6)^'DCF'!$J$15-'DCF'!$C$61-'DCF'!$C$62)/'DCF'!$C$64*100 | G6: =('DCF'!$F$14/(1+$C6)^'DCF'!$F$15+'DCF'!$G$14/(1+$C6)^'DCF'!$G$15+'DCF'!$H$14/(1+$C6)^'DCF'!$H$15+'DCF'!$I$14/(1+$C6)^'DCF'!$I$15+'DCF'!$J$14/(1+$C6)^'DCF'!$J$15+('Sensitivity'!G26*(1+G$4)/($C6-G$4)+'Assumptions'!$C$39*'Assumptions'!$C$37*'Sensitivity'!G27*(1-'Assumptions'!$C$37)/(1+$C6)/(1-(1-'Assumptions'!$C$37)/(1+$C6)))/(1+$C6)^'DCF'!$J$15-'DCF'!$C$61-'DCF'!$C$62)/'DCF'!$C$64*100 | H6: =('DCF'!$F$14/(1+$C6)^'DCF'!$F$15+'DCF'!$G$14/(1+$C6)^'DCF'!$G$15+'DCF'!$H$14/(1+$C6)^'DCF'!$H$15+'DCF'!$I$14/(1+$C6)^'DCF'!$I$15+'DCF'!$J$14/(1+$C6)^'DCF'!$J$15+('Sensitivity'!H26*(1+H$4)/($C6-H$4)+'Assumptions'!$C$39*'Assumptions'!$C$37*'Sensitivity'!H27*(1-'Assumptions'!$C$37)/(1+$C6)/(1-(1-'Assumptions'!$C$37)/(1+$C6)))/(1+$C6)^'DCF'!$J$15-'DCF'!$C$61-'DCF'!$C$62)/'DCF'!$C$64*100
B7: WACC (the model's own) | C7: ='DCF'!$C$5 | D7: =('DCF'!$F$14/(1+$C7)^'DCF'!$F$15+'DCF'!$G$14/(1+$C7)^'DCF'!$G$15+'DCF'!$H$14/(1+$C7)^'DCF'!$H$15+'DCF'!$I$14/(1+$C7)^'DCF'!$I$15+'DCF'!$J$14/(1+$C7)^'DCF'!$J$15+('Sensitivity'!D26*(1+D$4)/($C7-D$4)+'Assumptions'!$C$39*'Assumptions'!$C$37*'Sensitivity'!D27*(1-'Assumptions'!$C$37)/(1+$C7)/(1-(1-'Assumptions'!$C$37)/(1+$C7)))/(1+$C7)^'DCF'!$J$15-'DCF'!$C$61-'DCF'!$C$62)/'DCF'!$C$64*100 | E7: =('DCF'!$F$14/(1+$C7)^'DCF'!$F$15+'DCF'!$G$14/(1+$C7)^'DCF'!$G$15+'DCF'!$H$14/(1+$C7)^'DCF'!$H$15+'DCF'!$I$14/(1+$C7)^'DCF'!$I$15+'DCF'!$J$14/(1+$C7)^'DCF'!$J$15+('Sensitivity'!E26*(1+E$4)/($C7-E$4)+'Assumptions'!$C$39*'Assumptions'!$C$37*'Sensitivity'!E27*(1-'Assumptions'!$C$37)/(1+$C7)/(1-(1-'Assumptions'!$C$37)/(1+$C7)))/(1+$C7)^'DCF'!$J$15-'DCF'!$C$61-'DCF'!$C$62)/'DCF'!$C$64*100 | F7: =('DCF'!$F$14/(1+$C7)^'DCF'!$F$15+'DCF'!$G$14/(1+$C7)^'DCF'!$G$15+'DCF'!$H$14/(1+$C7)^'DCF'!$H$15+'DCF'!$I$14/(1+$C7)^'DCF'!$I$15+'DCF'!$J$14/(1+$C7)^'DCF'!$J$15+('Sensitivity'!F26*(1+F$4)/($C7-F$4)+'Assumptions'!$C$39*'Assumptions'!$C$37*'Sensitivity'!F27*(1-'Assumptions'!$C$37)/(1+$C7)/(1-(1-'Assumptions'!$C$37)/(1+$C7)))/(1+$C7)^'DCF'!$J$15-'DCF'!$C$61-'DCF'!$C$62)/'DCF'!$C$64*100 | G7: =('DCF'!$F$14/(1+$C7)^'DCF'!$F$15+'DCF'!$G$14/(1+$C7)^'DCF'!$G$15+'DCF'!$H$14/(1+$C7)^'DCF'!$H$15+'DCF'!$I$14/(1+$C7)^'DCF'!$I$15+'DCF'!$J$14/(1+$C7)^'DCF'!$J$15+('Sensitivity'!G26*(1+G$4)/($C7-G$4)+'Assumptions'!$C$39*'Assumptions'!$C$37*'Sensitivity'!G27*(1-'Assumptions'!$C$37)/(1+$C7)/(1-(1-'Assumptions'!$C$37)/(1+$C7)))/(1+$C7)^'DCF'!$J$15-'DCF'!$C$61-'DCF'!$C$62)/'DCF'!$C$64*100 | H7: =('DCF'!$F$14/(1+$C7)^'DCF'!$F$15+'DCF'!$G$14/(1+$C7)^'DCF'!$G$15+'DCF'!$H$14/(1+$C7)^'DCF'!$H$15+'DCF'!$I$14/(1+$C7)^'DCF'!$I$15+'DCF'!$J$14/(1+$C7)^'DCF'!$J$15+('Sensitivity'!H26*(1+H$4)/($C7-H$4)+'Assumptions'!$C$39*'Assumptions'!$C$37*'Sensitivity'!H27*(1-'Assumptions'!$C$37)/(1+$C7)/(1-(1-'Assumptions'!$C$37)/(1+$C7)))/(1+$C7)^'DCF'!$J$15-'DCF'!$C$61-'DCF'!$C$62)/'DCF'!$C$64*100
B8: WACC plus 50bp | C8: ='DCF'!$C$5+0.005 | D8: =('DCF'!$F$14/(1+$C8)^'DCF'!$F$15+'DCF'!$G$14/(1+$C8)^'DCF'!$G$15+'DCF'!$H$14/(1+$C8)^'DCF'!$H$15+'DCF'!$I$14/(1+$C8)^'DCF'!$I$15+'DCF'!$J$14/(1+$C8)^'DCF'!$J$15+('Sensitivity'!D26*(1+D$4)/($C8-D$4)+'Assumptions'!$C$39*'Assumptions'!$C$37*'Sensitivity'!D27*(1-'Assumptions'!$C$37)/(1+$C8)/(1-(1-'Assumptions'!$C$37)/(1+$C8)))/(1+$C8)^'DCF'!$J$15-'DCF'!$C$61-'DCF'!$C$62)/'DCF'!$C$64*100 | E8: =('DCF'!$F$14/(1+$C8)^'DCF'!$F$15+'DCF'!$G$14/(1+$C8)^'DCF'!$G$15+'DCF'!$H$14/(1+$C8)^'DCF'!$H$15+'DCF'!$I$14/(1+$C8)^'DCF'!$I$15+'DCF'!$J$14/(1+$C8)^'DCF'!$J$15+('Sensitivity'!E26*(1+E$4)/($C8-E$4)+'Assumptions'!$C$39*'Assumptions'!$C$37*'Sensitivity'!E27*(1-'Assumptions'!$C$37)/(1+$C8)/(1-(1-'Assumptions'!$C$37)/(1+$C8)))/(1+$C8)^'DCF'!$J$15-'DCF'!$C$61-'DCF'!$C$62)/'DCF'!$C$64*100 | F8: =('DCF'!$F$14/(1+$C8)^'DCF'!$F$15+'DCF'!$G$14/(1+$C8)^'DCF'!$G$15+'DCF'!$H$14/(1+$C8)^'DCF'!$H$15+'DCF'!$I$14/(1+$C8)^'DCF'!$I$15+'DCF'!$J$14/(1+$C8)^'DCF'!$J$15+('Sensitivity'!F26*(1+F$4)/($C8-F$4)+'Assumptions'!$C$39*'Assumptions'!$C$37*'Sensitivity'!F27*(1-'Assumptions'!$C$37)/(1+$C8)/(1-(1-'Assumptions'!$C$37)/(1+$C8)))/(1+$C8)^'DCF'!$J$15-'DCF'!$C$61-'DCF'!$C$62)/'DCF'!$C$64*100 | G8: =('DCF'!$F$14/(1+$C8)^'DCF'!$F$15+'DCF'!$G$14/(1+$C8)^'DCF'!$G$15+'DCF'!$H$14/(1+$C8)^'DCF'!$H$15+'DCF'!$I$14/(1+$C8)^'DCF'!$I$15+'DCF'!$J$14/(1+$C8)^'DCF'!$J$15+('Sensitivity'!G26*(1+G$4)/($C8-G$4)+'Assumptions'!$C$39*'Assumptions'!$C$37*'Sensitivity'!G27*(1-'Assumptions'!$C$37)/(1+$C8)/(1-(1-'Assumptions'!$C$37)/(1+$C8)))/(1+$C8)^'DCF'!$J$15-'DCF'!$C$61-'DCF'!$C$62)/'DCF'!$C$64*100 | H8: =('DCF'!$F$14/(1+$C8)^'DCF'!$F$15+'DCF'!$G$14/(1+$C8)^'DCF'!$G$15+'DCF'!$H$14/(1+$C8)^'DCF'!$H$15+'DCF'!$I$14/(1+$C8)^'DCF'!$I$15+'DCF'!$J$14/(1+$C8)^'DCF'!$J$15+('Sensitivity'!H26*(1+H$4)/($C8-H$4)+'Assumptions'!$C$39*'Assumptions'!$C$37*'Sensitivity'!H27*(1-'Assumptions'!$C$37)/(1+$C8)/(1-(1-'Assumptions'!$C$37)/(1+$C8)))/(1+$C8)^'DCF'!$J$15-'DCF'!$C$61-'DCF'!$C$62)/'DCF'!$C$64*100
B9: WACC plus 100bp | C9: ='DCF'!$C$5+0.01 | D9: =('DCF'!$F$14/(1+$C9)^'DCF'!$F$15+'DCF'!$G$14/(1+$C9)^'DCF'!$G$15+'DCF'!$H$14/(1+$C9)^'DCF'!$H$15+'DCF'!$I$14/(1+$C9)^'DCF'!$I$15+'DCF'!$J$14/(1+$C9)^'DCF'!$J$15+('Sensitivity'!D26*(1+D$4)/($C9-D$4)+'Assumptions'!$C$39*'Assumptions'!$C$37*'Sensitivity'!D27*(1-'Assumptions'!$C$37)/(1+$C9)/(1-(1-'Assumptions'!$C$37)/(1+$C9)))/(1+$C9)^'DCF'!$J$15-'DCF'!$C$61-'DCF'!$C$62)/'DCF'!$C$64*100 | E9: =('DCF'!$F$14/(1+$C9)^'DCF'!$F$15+'DCF'!$G$14/(1+$C9)^'DCF'!$G$15+'DCF'!$H$14/(1+$C9)^'DCF'!$H$15+'DCF'!$I$14/(1+$C9)^'DCF'!$I$15+'DCF'!$J$14/(1+$C9)^'DCF'!$J$15+('Sensitivity'!E26*(1+E$4)/($C9-E$4)+'Assumptions'!$C$39*'Assumptions'!$C$37*'Sensitivity'!E27*(1-'Assumptions'!$C$37)/(1+$C9)/(1-(1-'Assumptions'!$C$37)/(1+$C9)))/(1+$C9)^'DCF'!$J$15-'DCF'!$C$61-'DCF'!$C$62)/'DCF'!$C$64*100 | F9: =('DCF'!$F$14/(1+$C9)^'DCF'!$F$15+'DCF'!$G$14/(1+$C9)^'DCF'!$G$15+'DCF'!$H$14/(1+$C9)^'DCF'!$H$15+'DCF'!$I$14/(1+$C9)^'DCF'!$I$15+'DCF'!$J$14/(1+$C9)^'DCF'!$J$15+('Sensitivity'!F26*(1+F$4)/($C9-F$4)+'Assumptions'!$C$39*'Assumptions'!$C$37*'Sensitivity'!F27*(1-'Assumptions'!$C$37)/(1+$C9)/(1-(1-'Assumptions'!$C$37)/(1+$C9)))/(1+$C9)^'DCF'!$J$15-'DCF'!$C$61-'DCF'!$C$62)/'DCF'!$C$64*100 | G9: =('DCF'!$F$14/(1+$C9)^'DCF'!$F$15+'DCF'!$G$14/(1+$C9)^'DCF'!$G$15+'DCF'!$H$14/(1+$C9)^'DCF'!$H$15+'DCF'!$I$14/(1+$C9)^'DCF'!$I$15+'DCF'!$J$14/(1+$C9)^'DCF'!$J$15+('Sensitivity'!G26*(1+G$4)/($C9-G$4)+'Assumptions'!$C$39*'Assumptions'!$C$37*'Sensitivity'!G27*(1-'Assumptions'!$C$37)/(1+$C9)/(1-(1-'Assumptions'!$C$37)/(1+$C9)))/(1+$C9)^'DCF'!$J$15-'DCF'!$C$61-'DCF'!$C$62)/'DCF'!$C$64*100 | H9: =('DCF'!$F$14/(1+$C9)^'DCF'!$F$15+'DCF'!$G$14/(1+$C9)^'DCF'!$G$15+'DCF'!$H$14/(1+$C9)^'DCF'!$H$15+'DCF'!$I$14/(1+$C9)^'DCF'!$I$15+'DCF'!$J$14/(1+$C9)^'DCF'!$J$15+('Sensitivity'!H26*(1+H$4)/($C9-H$4)+'Assumptions'!$C$39*'Assumptions'!$C$37*'Sensitivity'!H27*(1-'Assumptions'!$C$37)/(1+$C9)/(1-(1-'Assumptions'!$C$37)/(1+$C9)))/(1+$C9)^'DCF'!$J$15-'DCF'!$C$61-'DCF'!$C$62)/'DCF'!$C$64*100
A11: Implied terminal EV/EBITDA — the same pairs, read as the multiple the Gordon value puts on terminal EBITDA
B12: Implied terminal multiple at WACC less 100bp | C12: ='DCF'!$C$5-0.01 | D12: ='Sensitivity'!D26*(1+D$4)/($C12-D$4)/'DCF'!$C$34 | E12: ='Sensitivity'!E26*(1+E$4)/($C12-E$4)/'DCF'!$C$34 | F12: ='Sensitivity'!F26*(1+F$4)/($C12-F$4)/'DCF'!$C$34 | G12: ='Sensitivity'!G26*(1+G$4)/($C12-G$4)/'DCF'!$C$34 | H12: ='Sensitivity'!H26*(1+H$4)/($C12-H$4)/'DCF'!$C$34
B13: Implied terminal multiple at WACC less 50bp | C13: ='DCF'!$C$5-0.005 | D13: ='Sensitivity'!D26*(1+D$4)/($C13-D$4)/'DCF'!$C$34 | E13: ='Sensitivity'!E26*(1+E$4)/($C13-E$4)/'DCF'!$C$34 | F13: ='Sensitivity'!F26*(1+F$4)/($C13-F$4)/'DCF'!$C$34 | G13: ='Sensitivity'!G26*(1+G$4)/($C13-G$4)/'DCF'!$C$34 | H13: ='Sensitivity'!H26*(1+H$4)/($C13-H$4)/'DCF'!$C$34
B14: Implied terminal multiple at WACC (the model's own) | C14: ='DCF'!$C$5 | D14: ='Sensitivity'!D26*(1+D$4)/($C14-D$4)/'DCF'!$C$34 | E14: ='Sensitivity'!E26*(1+E$4)/($C14-E$4)/'DCF'!$C$34 | F14: ='Sensitivity'!F26*(1+F$4)/($C14-F$4)/'DCF'!$C$34 | G14: ='Sensitivity'!G26*(1+G$4)/($C14-G$4)/'DCF'!$C$34 | H14: ='Sensitivity'!H26*(1+H$4)/($C14-H$4)/'DCF'!$C$34
B15: Implied terminal multiple at WACC plus 50bp | C15: ='DCF'!$C$5+0.005 | D15: ='Sensitivity'!D26*(1+D$4)/($C15-D$4)/'DCF'!$C$34 | E15: ='Sensitivity'!E26*(1+E$4)/($C15-E$4)/'DCF'!$C$34 | F15: ='Sensitivity'!F26*(1+F$4)/($C15-F$4)/'DCF'!$C$34 | G15: ='Sensitivity'!G26*(1+G$4)/($C15-G$4)/'DCF'!$C$34 | H15: ='Sensitivity'!H26*(1+H$4)/($C15-H$4)/'DCF'!$C$34
B16: Implied terminal multiple at WACC plus 100bp | C16: ='DCF'!$C$5+0.01 | D16: ='Sensitivity'!D26*(1+D$4)/($C16-D$4)/'DCF'!$C$34 | E16: ='Sensitivity'!E26*(1+E$4)/($C16-E$4)/'DCF'!$C$34 | F16: ='Sensitivity'!F26*(1+F$4)/($C16-F$4)/'DCF'!$C$34 | G16: ='Sensitivity'!G26*(1+G$4)/($C16-G$4)/'DCF'!$C$34 | H16: ='Sensitivity'!H26*(1+H$4)/($C16-H$4)/'DCF'!$C$34
B17: For comparison: peer median EV/EBITDA (a TRAILING multiple, from Comps) | C17: ='Comps'!$J$17
B18: For comparison: exit EV/EBITDA derived from the peer median EV/EBIT | C18: ='Comps'!$C$55
A20: Workings — the terminal year rebuilt at each growth rate above, one column per rate, aligned with the grids
B21: Terminal PP&E / revenue (post-programme anchor at this growth rate) | D21: =('BS'!J3/'IS'!J3)/(1+D$4)^(1/'Assumptions'!$C$37) | E21: =('BS'!J3/'IS'!J3)/(1+E$4)^(1/'Assumptions'!$C$37) | F21: =('BS'!J3/'IS'!J3)/(1+F$4)^(1/'Assumptions'!$C$37) | G21: =('BS'!J3/'IS'!J3)/(1+G$4)^(1/'Assumptions'!$C$37) | H21: =('BS'!J3/'IS'!J3)/(1+H$4)^(1/'Assumptions'!$C$37)
B22: Terminal total capex (% of revenue, sustaining at this growth rate) | D22: ='Sensitivity'!D21*(D$4+'Assumptions'!$C$37)/(1+D$4)/'Assumptions'!$C$59 | E22: ='Sensitivity'!E21*(E$4+'Assumptions'!$C$37)/(1+E$4)/'Assumptions'!$C$59 | F22: ='Sensitivity'!F21*(F$4+'Assumptions'!$C$37)/(1+F$4)/'Assumptions'!$C$59 | G22: ='Sensitivity'!G21*(G$4+'Assumptions'!$C$37)/(1+G$4)/'Assumptions'!$C$59 | H22: ='Sensitivity'!H21*(H$4+'Assumptions'!$C$37)/(1+H$4)/'Assumptions'!$C$59
B23: Terminal D&A (% of revenue: PP&E + ROU depreciation + amortisation) | D23: ='Assumptions'!$C$37*'Sensitivity'!D21/(1+D$4)+'Assumptions'!$C$38*'DCF'!$C$23/(1+D$4)+'Sensitivity'!D22*'Assumptions'!$C$58*'Assumptions'!$C$60/(D$4+'Assumptions'!$C$60) | E23: ='Assumptions'!$C$37*'Sensitivity'!E21/(1+E$4)+'Assumptions'!$C$38*'DCF'!$C$23/(1+E$4)+'Sensitivity'!E22*'Assumptions'!$C$58*'Assumptions'!$C$60/(E$4+'Assumptions'!$C$60) | F23: ='Assumptions'!$C$37*'Sensitivity'!F21/(1+F$4)+'Assumptions'!$C$38*'DCF'!$C$23/(1+F$4)+'Sensitivity'!F22*'Assumptions'!$C$58*'Assumptions'!$C$60/(F$4+'Assumptions'!$C$60) | G23: ='Assumptions'!$C$37*'Sensitivity'!G21/(1+G$4)+'Assumptions'!$C$38*'DCF'!$C$23/(1+G$4)+'Sensitivity'!G22*'Assumptions'!$C$58*'Assumptions'!$C$60/(G$4+'Assumptions'!$C$60) | H23: ='Assumptions'!$C$37*'Sensitivity'!H21/(1+H$4)+'Assumptions'!$C$38*'DCF'!$C$23/(1+H$4)+'Sensitivity'!H22*'Assumptions'!$C$58*'Assumptions'!$C$60/(H$4+'Assumptions'!$C$60)
B24: Terminal depreciation and amortisation | D24: ='Sensitivity'!D23*'DCF'!$C$32 | E24: ='Sensitivity'!E23*'DCF'!$C$32 | F24: ='Sensitivity'!F23*'DCF'!$C$32 | G24: ='Sensitivity'!G23*'DCF'!$C$32 | H24: ='Sensitivity'!H23*'DCF'!$C$32
B25: Terminal EBIT (terminal EBITDA less the D&A above) | D25: ='DCF'!$C$34-'Sensitivity'!D24 | E25: ='DCF'!$C$34-'Sensitivity'!E24 | F25: ='DCF'!$C$34-'Sensitivity'!F24 | G25: ='DCF'!$C$34-'Sensitivity'!G24 | H25: ='DCF'!$C$34-'Sensitivity'!H24
B26: Terminal unlevered free cash flow | D26: ='Sensitivity'!D25*(1-'Assumptions'!$C$39)+'Sensitivity'!D24-'Sensitivity'!D22*'DCF'!$C$32-'DCF'!$C$23*(D$4+'Assumptions'!$C$38)/(1+D$4)*'DCF'!$C$32-'DCF'!$C$31*D$4/(1+D$4)*'DCF'!$C$32 | E26: ='Sensitivity'!E25*(1-'Assumptions'!$C$39)+'Sensitivity'!E24-'Sensitivity'!E22*'DCF'!$C$32-'DCF'!$C$23*(E$4+'Assumptions'!$C$38)/(1+E$4)*'DCF'!$C$32-'DCF'!$C$31*E$4/(1+E$4)*'DCF'!$C$32 | F26: ='Sensitivity'!F25*(1-'Assumptions'!$C$39)+'Sensitivity'!F24-'Sensitivity'!F22*'DCF'!$C$32-'DCF'!$C$23*(F$4+'Assumptions'!$C$38)/(1+F$4)*'DCF'!$C$32-'DCF'!$C$31*F$4/(1+F$4)*'DCF'!$C$32 | G26: ='Sensitivity'!G25*(1-'Assumptions'!$C$39)+'Sensitivity'!G24-'Sensitivity'!G22*'DCF'!$C$32-'DCF'!$C$23*(G$4+'Assumptions'!$C$38)/(1+G$4)*'DCF'!$C$32-'DCF'!$C$31*G$4/(1+G$4)*'DCF'!$C$32 | H26: ='Sensitivity'!H25*(1-'Assumptions'!$C$39)+'Sensitivity'!H24-'Sensitivity'!H22*'DCF'!$C$32-'DCF'!$C$23*(H$4+'Assumptions'!$C$38)/(1+H$4)*'DCF'!$C$32-'DCF'!$C$31*H$4/(1+H$4)*'DCF'!$C$32
B27: Excess PP&E over this growth rate's re-based base, at FY2029 | D27: ='BS'!I3-'Sensitivity'!D21*'IS'!I3 | E27: ='BS'!I3-'Sensitivity'!E21*'IS'!I3 | F27: ='BS'!I3-'Sensitivity'!F21*'IS'!I3 | G27: ='BS'!I3-'Sensitivity'!G21*'IS'!I3 | H27: ='BS'!I3-'Sensitivity'!H21*'IS'!I3
B28: Check: centre column's terminal FCF less the DCF's own (must be nil) | C28: ='Sensitivity'!F26-'DCF'!$C$40

Sheet Comps
A1: Trading comparables — five UK-listed peers, post-IFRS 16, £m
C2: SSP Group | D2: Domino's Pizza Group | E2: J D Wetherspoon | F2: Mitchells & Butlers | G2: Whitbread | I2: Peer min | J2: Peer median | K2: Peer max
B3: Share price (pence) | C3: 212.4 | D3: 218 | E3: 814 | F3: 284.5 | G3: 2493
B4: Shares outstanding (m) | C4: 762.24 | D4: 381.16 | E4: 102.79 | F4: 593.93 | G4: 167.14
B5: Market capitalisation (£m) | C5: 1618.998 | D5: 830.929 | E5: 836.711 | F5: 1689.731 | G5: 4166.8
B6: Net debt including lease liabilities (£m) | C6: 1816.9 | D6: 524.7 | E6: 1129.1 | F6: 1277 | G6: 5232
B7: of which lease liabilities (£m) | C7: 1242.7 | D7: 240.1 | E7: 407.2 | F7: 434 | G7: 4523.1
B8: Minority interests (£m, book value) | C8: 186.8 | D8: -0.6 | E8: 0 | F8: 0 | G8: 0
B9: Enterprise value (£m) | C9: 3622.698 | D9: 1355.029 | E9: 1965.811 | F9: 2966.731 | G9: 9398.8
B10: EBITDA (£m, post-IFRS 16, underlying) | C10: 687.2 | D10: 133.9 | E10: 260.8 | F10: 465 | G10: 1076
B11: EBIT (£m, post-IFRS 16, underlying) | C11: 269.1 | D11: 111.2 | E11: 146.4 | F11: 330 | G11: 649
B12: Net income (£m, statutory, attributable) | C12: -74.4 | D12: 58.6 | E12: 68 | F12: 177 | G12: 212.9
B13: Check: price x shares less market capitalisation (£m, |x| < 0.01) | C13: ='Comps'!C3/100*'Comps'!C4-'Comps'!C5 | D13: ='Comps'!D3/100*'Comps'!D4-'Comps'!D5 | E13: ='Comps'!E3/100*'Comps'!E4-'Comps'!E5 | F13: ='Comps'!F3/100*'Comps'!F4-'Comps'!F5 | G13: ='Comps'!G3/100*'Comps'!G4-'Comps'!G5
B14: Check: market cap + net debt + minorities less EV (£m, |x| < 0.01) | C14: ='Comps'!C5+'Comps'!C6+'Comps'!C8-'Comps'!C9 | D14: ='Comps'!D5+'Comps'!D6+'Comps'!D8-'Comps'!D9 | E14: ='Comps'!E5+'Comps'!E6+'Comps'!E8-'Comps'!E9 | F14: ='Comps'!F5+'Comps'!F6+'Comps'!F8-'Comps'!F9 | G14: ='Comps'!G5+'Comps'!G6+'Comps'!G8-'Comps'!G9
B15: Implied D&A (£m, EBITDA less EBIT) | C15: ='Comps'!C10-'Comps'!C11 | D15: ='Comps'!D10-'Comps'!D11 | E15: ='Comps'!E10-'Comps'!E11 | F15: ='Comps'!F10-'Comps'!F11 | G15: ='Comps'!G10-'Comps'!G11
B16: D&A / EBITDA (capital intensity) | C16: =('Comps'!C10-'Comps'!C11)/'Comps'!C10 | D16: =('Comps'!D10-'Comps'!D11)/'Comps'!D10 | E16: =('Comps'!E10-'Comps'!E11)/'Comps'!E10 | F16: =('Comps'!F10-'Comps'!F11)/'Comps'!F10 | G16: =('Comps'!G10-'Comps'!G11)/'Comps'!G10 | I16: =MIN(C16:G16) | J16: =MEDIAN(C16:G16) | K16: =MAX(C16:G16)
B17: EV / EBITDA | C17: ='Comps'!C9/'Comps'!C10 | D17: ='Comps'!D9/'Comps'!D10 | E17: ='Comps'!E9/'Comps'!E10 | F17: ='Comps'!F9/'Comps'!F10 | G17: ='Comps'!G9/'Comps'!G10 | I17: =MIN(C17:G17) | J17: =MEDIAN(C17:G17) | K17: =MAX(C17:G17)
B18: EV / EBIT | C18: ='Comps'!C9/'Comps'!C11 | D18: ='Comps'!D9/'Comps'!D11 | E18: ='Comps'!E9/'Comps'!E11 | F18: ='Comps'!F9/'Comps'!F11 | G18: ='Comps'!G9/'Comps'!G11 | I18: =MIN(C18:G18) | J18: =MEDIAN(C18:G18) | K18: =MAX(C18:G18)
B19: P/E (SSP is a statutory loss and is excluded from the statistics) | C19: ='Comps'!C5/'Comps'!C12 | D19: ='Comps'!D5/'Comps'!D12 | E19: ='Comps'!E5/'Comps'!E12 | F19: ='Comps'!F5/'Comps'!F12 | G19: ='Comps'!G5/'Comps'!G12 | I19: =MIN(D19:G19) | J19: =MEDIAN(D19:G19) | K19: =MAX(D19:G19)
B20: Source (results announcement, then the price snapshot) | C20: SSP Group plc, '2025 Full Year Results Announcement' RNS, 4 December 2025, year ended 30 September 2025; price stockanalysis.com LON:SSPG 5 August 2026 11:45 GMT | D20: Domino's Pizza Group plc, 'Full year results for the 52 weeks ended 28.12.25' RNS, 10 March 2026; price stockanalysis.com LON:DOM 5 August 2026 11:59 GMT | E20: J D Wetherspoon plc, 'Preliminary Results' RNS, 3 October 2025, 52 weeks ended 27 July 2025; price stockanalysis.com LON:JDW 5 August 2026 11:54 GMT | F20: Mitchells & Butlers plc, 'Full Year Results' RNS, 28 November 2025, 52 weeks ended 27 September 2025; price stockanalysis.com LON:MAB 5 August 2026 11:52 GMT | G20: Whitbread PLC, 'Preliminary Results Announcement' RNS, 30 April 2026, 52 weeks ended 26 February 2026; price stockanalysis.com LON:WTB 5 August 2026 11:58 GMT | L20: Peer figures were read through a summarising fetcher, NOT line by line from the source documents, and carry no page references — see comps.py. Every EBIT above is a printed operating-profit line; three of the five EBITDAs are constructed.
B21: All six share prices were observed at | C21: 5 August 2026, 11:45-11:59 GMT
A23: Greggs plc at the observed market price, on the same basis
B24: Greggs share price (pence) | C24: 1964
B25: Greggs shares outstanding (m, price provider; the filing's diluted count is on Historicals) | C25: 101.96
B26: Greggs market capitalisation (£m) | C26: ='Comps'!$C$24/100*'Comps'!$C$25
B27: Greggs net debt including lease liabilities (£m, FY2025 actual) | C27: ='Historicals'!E31-'Historicals'!E25+'Historicals'!E30
B28: Greggs enterprise value (£m) | C28: ='Comps'!$C$26+'Comps'!$C$27
B29: Greggs EBITDA (£m, FY2025, the basis the model forecasts) | C29: ='Historicals'!E13
B30: Greggs EBIT (£m, FY2025, struck AFTER impairment — see below) | C30: ='Historicals'!E15
B31: Greggs net income (£m, FY2025) | C31: ='Historicals'!E17
B32: Greggs EV / EBITDA | C32: ='Comps'!$C$28/'Comps'!$C$29
B33: Greggs EV / EBIT | C33: ='Comps'!$C$28/'Comps'!$C$30
B34: Greggs P/E | C34: ='Comps'!$C$26/'Comps'!$C$31
B35: Discount to the peer median on EV/EBITDA (negative = cheaper) | C35: ='Comps'!$C$32/'Comps'!$J$17-1
B36: Discount to the peer median on EV/EBIT (NOT like for like — see impairment below) | C36: ='Comps'!$C$33/'Comps'!$J$18-1
A38: Impairment asymmetry on EBIT — a known bias, and it flatters the model
B39: FY2025 net impairment of PP&E, inside depreciation (FY2025 AR p.148) | C39: 3.9
B40: FY2025 net impairment of ROU assets, inside depreciation (FY2025 AR p.148) | C40: 3
B41: FY2025 net impairment inside D&A (£m) | C41: ='Comps'!$C$39+'Comps'!$C$40
B42: Greggs EBIT on the peers' basis, before impairment (£m) | C42: ='Comps'!$C$30+'Comps'!$C$41
B43: Peers'-basis EV / EBIT (Greggs, before impairment) | C43: ='Comps'!$C$28/'Comps'!$C$42
B44: Discount to the peer median on the peers'-basis EV/EBIT (the like-for-like read) | C44: ='Comps'!$C$43/'Comps'!$J$18-1
A46: Comps-implied value, and the traded range it is read against
B47: Comps-implied share price at the peer minimum EV/EBITDA (p) | C47: =('Comps'!$C$29*'Comps'!$I$17-('Historicals'!E31-'Historicals'!E25)-'Historicals'!E30)/'Historicals'!E44*100
B48: Comps-implied share price at the peer median EV/EBITDA (p) | C48: =('Comps'!$C$29*'Comps'!$J$17-('Historicals'!E31-'Historicals'!E25)-'Historicals'!E30)/'Historicals'!E44*100
B49: Comps-implied share price at the peer maximum EV/EBITDA (p) | C49: =('Comps'!$C$29*'Comps'!$K$17-('Historicals'!E31-'Historicals'!E25)-'Historicals'!E30)/'Historicals'!E44*100
B50: 52-week low (pence, market observation, no formula source) | C50: 1407.2
B51: 52-week high (pence, market observation, no formula source) | C51: 2046
A53: The exit multiple this peer set implies (it SETS the driver)
B54: Terminal D&A / EBITDA, from the DCF's re-based terminal year | C54: ='DCF'!$C$41
B55: Derived exit EV/EBITDA (= peer median EV/EBIT x (1 - terminal D&A/EBITDA)) | C55: ='Comps'!$J$18*(1-'Comps'!$C$54)
B56: Exit EV/EBITDA as shipped on Assumptions (the derived figure, 2dp) | C56: ='Assumptions'!$C$31
B57: Rounding carried by the shipped driver (derived less shipped) | C57: ='Comps'!$C$55-'Comps'!$C$56
B58: The median of five observations IS one observation — here J D Wetherspoon, a majority-freehold pub company. Dropping any of the three highest names moves the EV/EBIT median by -4.6% (SSP or Whitbread) or -4.5% (JDW, which IS the median), which is the honest error bar on everything derived from it.
B59: Not one of the five is a close structural match to leased-estate food-to-go retail. SSP is the closest and the cheapest; Domino's is an asset-light franchisor and its 10.1x EV/EBITDA is an upper bound on franchise economics, not a comparable capital structure.
B60: PROVENANCE IS NOT SYMMETRIC: Greggs' figures were read line by line from the filings with page numbers; the peer figures were not, and have no page references. Internal ties bound transcription error only — they say nothing about whether the right line was selected.

Sheet LBO
A1: Leveraged buyout — sponsor returns on the model's own operating case, £m
F2: ='Assumptions'!F$2 | G2: ='Assumptions'!G$2 | H2: ='Assumptions'!H$2 | I2: ='Assumptions'!I$2 | J2: ='Assumptions'!J$2
B3: Entry enterprise value (Greggs' traded EV from Comps) | C3: ='Comps'!$C$28
B4: Entry EBITDA (FY2025, the basis the model forecasts) | C4: ='Historicals'!E13
B5: Entry EV/EBITDA | C5: ='LBO'!$C$3/'LBO'!$C$4
B6: Entry leverage (x EBITDA, total net debt INCLUDING leases) | C6: ='Assumptions'!$C$64
B7: Entry total net debt including leases | C7: ='LBO'!$C$6*'LBO'!$C$4
B8: of which the existing lease liability (already spoken for) | C8: ='Historicals'!E30
B9: new financial debt raised (the leverage less the leases) | C9: ='LBO'!$C$7-'LBO'!$C$8
B10: Sponsor equity cheque (entry EV less total entry debt) | C10: ='LBO'!$C$3-'LBO'!$C$7
A12: The hold — cash sweep against the new financial debt
B13: Unlevered free cash flow (the DCF's own, unchanged) | F13: ='DCF'!F14 | G13: ='DCF'!G14 | H13: ='DCF'!H14 | I13: ='DCF'!I14 | J13: ='DCF'!J14
B14: New ROU additions added back (a new lease funds its own asset) | F14: ='Schedules'!F25 | G14: ='Schedules'!G25 | H14: ='Schedules'!H25 | I14: ='Schedules'!I25 | J14: ='Schedules'!J25
B15: Lease principal repaid | F15: ='Schedules'!F30 | G15: ='Schedules'!G30 | H15: ='Schedules'!H30 | I15: ='Schedules'!I30 | J15: ='Schedules'!J30
B16: Lease interest | F16: ='Schedules'!F29 | G16: ='Schedules'!G29 | H16: ='Schedules'!H29 | I16: ='Schedules'!I29 | J16: ='Schedules'!J29
B17: Opening financial debt | F17: ='LBO'!$C$9 | G17: ='LBO'!F20 | H17: ='LBO'!G20 | I17: ='LBO'!H20 | J17: ='LBO'!I20
B18: Interest on financial debt (rate on the opening balance) | F18: ='LBO'!F17*'Assumptions'!$C$44 | G18: ='LBO'!G17*'Assumptions'!$C$44 | H18: ='LBO'!H17*'Assumptions'!$C$44 | I18: ='LBO'!I17*'Assumptions'!$C$44 | J18: ='LBO'!J17*'Assumptions'!$C$44
B19: Cash available to repay debt (negative draws more) | F19: ='LBO'!F13+'LBO'!F14-'LBO'!F15-'LBO'!F16*(1-'Assumptions'!$C$39)-'LBO'!F18*(1-'Assumptions'!$C$39) | G19: ='LBO'!G13+'LBO'!G14-'LBO'!G15-'LBO'!G16*(1-'Assumptions'!$C$39)-'LBO'!G18*(1-'Assumptions'!$C$39) | H19: ='LBO'!H13+'LBO'!H14-'LBO'!H15-'LBO'!H16*(1-'Assumptions'!$C$39)-'LBO'!H18*(1-'Assumptions'!$C$39) | I19: ='LBO'!I13+'LBO'!I14-'LBO'!I15-'LBO'!I16*(1-'Assumptions'!$C$39)-'LBO'!I18*(1-'Assumptions'!$C$39) | J19: ='LBO'!J13+'LBO'!J14-'LBO'!J15-'LBO'!J16*(1-'Assumptions'!$C$39)-'LBO'!J18*(1-'Assumptions'!$C$39)
B20: Closing financial debt | F20: ='LBO'!F17-'LBO'!F19 | G20: ='LBO'!G17-'LBO'!G19 | H20: ='LBO'!H17-'LBO'!H19 | I20: ='LBO'!I17-'LBO'!I19 | J20: ='LBO'!J17-'LBO'!J19
B21: Closing lease liabilities (the DCF's own lease book — it GROWS) | F21: ='Schedules'!F31 | G21: ='Schedules'!G31 | H21: ='Schedules'!H31 | I21: ='Schedules'!I31 | J21: ='Schedules'!J31
B22: Closing total debt including leases | F22: ='LBO'!F20+'LBO'!F21 | G22: ='LBO'!G20+'LBO'!G21 | H22: ='LBO'!H20+'LBO'!H21 | I22: ='LBO'!I20+'LBO'!I21 | J22: ='LBO'!J20+'LBO'!J21
B23: Closing total debt / that year's EBITDA | F23: ='LBO'!F22/'IS'!F7 | G23: ='LBO'!G22/'IS'!G7 | H23: ='LBO'!H22/'IS'!H7 | I23: ='LBO'!I22/'IS'!I7 | J23: ='LBO'!J22/'IS'!J7
A25: Exit — at the multiple paid, with no expansion assumed
B26: Exit EBITDA (FY2030) | C26: ='IS'!J7
B27: Exit EV/EBITDA (the entry multiple, unchanged) | C27: ='LBO'!$C$5
B28: Exit enterprise value | C28: ='LBO'!$C$27*'LBO'!$C$26
B29: Exit total net debt including leases | C29: ='LBO'!J22
B30: Exit equity value | C30: ='LBO'!$C$28-'LBO'!$C$29
B31: Hold period (years, = the length of the forecast) | C31: =COLUMNS(F13:J13)
B32: Money multiple (exit equity / entry equity) | C32: ='LBO'!$C$30/'LBO'!$C$10
B33: IRR (geometric: one cheque in, one out) | C33: ='LBO'!$C$32^(1/'LBO'!$C$31)-1
B34: IRR less the sponsor hurdle (negative = below it) | C34: ='LBO'!$C$33-'Assumptions'!$C$65
B35: Exit EV/EBITDA that would clear the hurdle (against the entry multiple above) | C35: =('LBO'!$C$10*(1+'Assumptions'!$C$65)^'LBO'!$C$31+'LBO'!$C$29)/'LBO'!$C$26
B36: Change in total debt over the hold (exit less entry, £m; positive = debt GREW) | C36: ='LBO'!$C$29-'LBO'!$C$7
B37: EBITDA growth over the hold | C37: ='LBO'!$C$26/'LBO'!$C$4-1
B38: Read the two rows above together. De-gearing contributes nothing to the return in any scenario and works against it in two: total debt including leases ends £208.7m HIGHER in Bear and £118.2m higher in Base, and only £6.8m lower in Bull, against an equity cheque of £1,001.7m. The money multiple is therefore essentially an EBITDA-growth story applied to a static multiple. Unlevered free cash flow is negative in FY2026 in every scenario (and in FY2027 too in Bear and Base) while the distribution-centre programme runs, so the sponsor FUNDS capex rather than sweeping cash against the debt; and the lease book grows in all three, because the model opens more shops than it closes.
B39: This sheet CANNOT corroborate the DCF: the free cash flow row above is the DCF's own row, so both are wrong together or right together. It is the same cash flows re-expressed levered and inside a five-year window, which is why the terminal-value concentration on the DCF sheet shows up here as a low IRR. It also carries no control premium and no fees, both of which flatter it — lbo.py quantifies each.

Sheet Football Field
A1: Football field — valuation ranges, pence per share
C3: Low | D3: High | E3: Span | F3: Central
B4: DCF (Gordon) — WACC +/-100bp, perpetuity growth +/-50bp | C4: =MIN('Sensitivity'!D5:H5,'Sensitivity'!D6:H6,'Sensitivity'!D7:H7,'Sensitivity'!D8:H8,'Sensitivity'!D9:H9) | D4: =MAX('Sensitivity'!D5:H5,'Sensitivity'!D6:H6,'Sensitivity'!D7:H7,'Sensitivity'!D8:H8,'Sensitivity'!D9:H9) | E4: =D4-C4 | F4: ='DCF'!$C$65
B5: Trading comps — peer minimum to peer maximum EV/EBITDA | C5: ='Comps'!$C$47 | D5: ='Comps'!$C$49 | E5: =D5-C5 | F5: ='Comps'!$C$48
B6: 52-week traded range — the market's own answer | C6: ='Comps'!$C$50 | D6: ='Comps'!$C$51 | E6: =D6-C6 | F6: ='Comps'!$C$24
B8: There is deliberately NO exit-multiple bar. The exit multiple is derived as peer median EV/EBIT x (1 - terminal D&A/EBITDA), and since EV/EBITDA = EV/EBIT x (1 - D&A/EBITDA) is an identity, its terminal value is arithmetically the peer median EV/EBIT applied to terminal EBIT. Drawn beside the Gordon bar it would present one peer statistic, already carried by the comps bar, as a second independent method.
B9: The 52-week range and the traded price are market observations from one provider on one date -- see the observation date on Comps. They are the only figures in this workbook that are wrong tomorrow rather than merely out of date at the next reporting cycle. Re-read them before showing this sheet to anyone.
B10: A wider bar is not a less confident method. The comps bar spans the peer minimum to maximum across five names, none of which is a close structural match for leased-estate food-to-go; the DCF bar spans a deliberately chosen +/-100bp of WACC. They are different kinds of range and should not be compared by width.
